{
"meta":{"test_sets":[],"test_metrics":[],"learn_metrics":[{"best_value":"Min","name":"RMSE"}],"launch_mode":"Train","parameters":"","iteration_count":1000,"learn_sets":["learn"],"name":"experiment"},
"iterations":[
{"learn":[5184.740435],"iteration":0,"passed_time":0.001573629493,"remaining_time":1.572055864},
{"learn":[5115.348811],"iteration":1,"passed_time":0.002708041232,"remaining_time":1.351312575},
{"learn":[5025.30884],"iteration":2,"passed_time":0.003833877536,"remaining_time":1.274125301},
{"learn":[4951.114098],"iteration":3,"passed_time":0.004924831057,"remaining_time":1.226282933},
{"learn":[4876.527995],"iteration":4,"passed_time":0.006021925631,"remaining_time":1.198363201},
{"learn":[4802.563846],"iteration":5,"passed_time":0.007147020601,"remaining_time":1.18402308},
{"learn":[4739.123215],"iteration":6,"passed_time":0.008205585829,"remaining_time":1.164020961},
{"learn":[4670.974919],"iteration":7,"passed_time":0.00925065677,"remaining_time":1.14708144},
{"learn":[4600.950324],"iteration":8,"passed_time":0.0102839966,"remaining_time":1.132382292},
{"learn":[4523.872569],"iteration":9,"passed_time":0.01133908557,"remaining_time":1.122569471},
{"learn":[4457.326276],"iteration":10,"passed_time":0.01236664499,"remaining_time":1.111873809},
{"learn":[4396.443321],"iteration":11,"passed_time":0.01344277183,"remaining_time":1.106788214},
{"learn":[4336.269431],"iteration":12,"passed_time":0.01463784274,"remaining_time":1.111350061},
{"learn":[4263.687467],"iteration":13,"passed_time":0.01569726952,"remaining_time":1.105536268},
{"learn":[4206.616669],"iteration":14,"passed_time":0.01676982994,"remaining_time":1.101218833},
{"learn":[4146.972548],"iteration":15,"passed_time":0.01782607098,"remaining_time":1.096303365},
{"learn":[4088.364937],"iteration":16,"passed_time":0.01888446591,"remaining_time":1.09196647},
{"learn":[4031.09968],"iteration":17,"passed_time":0.01993803214,"remaining_time":1.08773042},
{"learn":[3963.306452],"iteration":18,"passed_time":0.02099059656,"remaining_time":1.083777644},
{"learn":[3903.774288],"iteration":19,"passed_time":0.02206457954,"remaining_time":1.081164398},
{"learn":[3843.42462],"iteration":20,"passed_time":0.02321552103,"remaining_time":1.08228548},
{"learn":[3798.113359],"iteration":21,"passed_time":0.02428667892,"remaining_time":1.079653272},
{"learn":[3734.315263],"iteration":22,"passed_time":0.02532255331,"remaining_time":1.075658025},
{"learn":[3678.800435],"iteration":23,"passed_time":0.02640138778,"remaining_time":1.073656436},
{"learn":[3630.110677],"iteration":24,"passed_time":0.02749344467,"remaining_time":1.072244342},
{"learn":[3574.933641],"iteration":25,"passed_time":0.02857047313,"remaining_time":1.070293878},
{"learn":[3531.347875],"iteration":26,"passed_time":0.02964077949,"remaining_time":1.068165868},
{"learn":[3478.599024],"iteration":27,"passed_time":0.03071973141,"remaining_time":1.066413533},
{"learn":[3427.213812],"iteration":28,"passed_time":0.03177350802,"remaining_time":1.063864699},
{"learn":[3384.956466],"iteration":29,"passed_time":0.03283502856,"remaining_time":1.061665924},
{"learn":[3350.331275],"iteration":30,"passed_time":0.03388557937,"remaining_time":1.059197626},
{"learn":[3310.583369],"iteration":31,"passed_time":0.03493454732,"remaining_time":1.056770056},
{"learn":[3264.532308],"iteration":32,"passed_time":0.03600416244,"remaining_time":1.055031063},
{"learn":[3224.180677],"iteration":33,"passed_time":0.03706450086,"remaining_time":1.053067877},
{"learn":[3179.493211],"iteration":34,"passed_time":0.03813821335,"remaining_time":1.051525025},
{"learn":[3136.317011],"iteration":35,"passed_time":0.03924936322,"remaining_time":1.051010726},
{"learn":[3099.293934],"iteration":36,"passed_time":0.04030679641,"remaining_time":1.04906608},
{"learn":[3062.932],"iteration":37,"passed_time":0.04138884977,"remaining_time":1.047791407},
{"learn":[3023.398604],"iteration":38,"passed_time":0.04248847891,"remaining_time":1.046959698},
{"learn":[2987.965863],"iteration":39,"passed_time":0.04353826834,"remaining_time":1.04491844},
{"learn":[2947.536935],"iteration":40,"passed_time":0.0445924056,"remaining_time":1.043027243},
{"learn":[2918.103077],"iteration":41,"passed_time":0.04565537876,"remaining_time":1.041377449},
{"learn":[2883.04516],"iteration":42,"passed_time":0.04675633028,"remaining_time":1.040600188},
{"learn":[2852.673115],"iteration":43,"passed_time":0.04782178791,"remaining_time":1.039037028},
{"learn":[2822.238578],"iteration":44,"passed_time":0.04895699108,"remaining_time":1.038976144},
{"learn":[2787.542721],"iteration":45,"passed_time":0.05010092996,"remaining_time":1.039049721},
{"learn":[2756.892371],"iteration":46,"passed_time":0.05115598888,"remaining_time":1.037269306},
{"learn":[2724.393241],"iteration":47,"passed_time":0.05221041666,"remaining_time":1.035506597},
{"learn":[2688.772056],"iteration":48,"passed_time":0.05328171481,"remaining_time":1.03410022},
{"learn":[2654.142282],"iteration":49,"passed_time":0.05435889354,"remaining_time":1.032818977},
{"learn":[2625.341963],"iteration":50,"passed_time":0.05550287249,"remaining_time":1.032788745},
{"learn":[2600.582002],"iteration":51,"passed_time":0.0567347424,"remaining_time":1.034317996},
{"learn":[2572.864364],"iteration":52,"passed_time":0.05827592625,"remaining_time":1.041269852},
{"learn":[2544.50119],"iteration":53,"passed_time":0.05958473187,"remaining_time":1.043836229},
{"learn":[2515.530733],"iteration":54,"passed_time":0.06081492738,"remaining_time":1.044911025},
{"learn":[2491.316333],"iteration":55,"passed_time":0.06224651398,"remaining_time":1.049298379},
{"learn":[2462.104643],"iteration":56,"passed_time":0.06353882854,"remaining_time":1.051177462},
{"learn":[2431.217167],"iteration":57,"passed_time":0.06480801422,"remaining_time":1.052571541},
{"learn":[2405.971978],"iteration":58,"passed_time":0.06613521156,"remaining_time":1.054800578},
{"learn":[2382.863168],"iteration":59,"passed_time":0.06731454139,"remaining_time":1.054594482},
{"learn":[2357.745117],"iteration":60,"passed_time":0.06852253556,"remaining_time":1.05479772},
{"learn":[2336.989926],"iteration":61,"passed_time":0.06981192554,"remaining_time":1.056186874},
{"learn":[2318.472893],"iteration":62,"passed_time":0.07108134026,"remaining_time":1.057193902},
{"learn":[2295.082421],"iteration":63,"passed_time":0.07227256425,"remaining_time":1.056986252},
{"learn":[2272.210447],"iteration":64,"passed_time":0.07351558146,"remaining_time":1.057493364},
{"learn":[2248.085084],"iteration":65,"passed_time":0.07479967259,"remaining_time":1.0585287},
{"learn":[2226.515169],"iteration":66,"passed_time":0.07603358341,"remaining_time":1.05879602},
{"learn":[2200.029076],"iteration":67,"passed_time":0.07717638024,"remaining_time":1.057770388},
{"learn":[2178.613513],"iteration":68,"passed_time":0.07827161146,"remaining_time":1.056099569},
{"learn":[2155.516161],"iteration":69,"passed_time":0.07932470685,"remaining_time":1.053885391},
{"learn":[2135.1727],"iteration":70,"passed_time":0.08041202382,"remaining_time":1.052151692},
{"learn":[2117.171892],"iteration":71,"passed_time":0.08144649569,"remaining_time":1.049754833},
{"learn":[2095.664988],"iteration":72,"passed_time":0.08251810439,"remaining_time":1.047866887},
{"learn":[2076.440913],"iteration":73,"passed_time":0.08360607254,"remaining_time":1.046205719},
{"learn":[2056.742666],"iteration":74,"passed_time":0.08481155219,"remaining_time":1.046009144},
{"learn":[2037.145148],"iteration":75,"passed_time":0.08617006727,"remaining_time":1.047646607},
{"learn":[2019.431583],"iteration":76,"passed_time":0.08744306845,"remaining_time":1.048181197},
{"learn":[2003.226618],"iteration":77,"passed_time":0.08863817943,"remaining_time":1.047748736},
{"learn":[1987.707242],"iteration":78,"passed_time":0.08988469294,"remaining_time":1.04789623},
{"learn":[1971.035518],"iteration":79,"passed_time":0.09110517959,"remaining_time":1.047709565},
{"learn":[1957.297726],"iteration":80,"passed_time":0.0923158586,"remaining_time":1.047386099},
{"learn":[1943.778906],"iteration":81,"passed_time":0.0934805849,"remaining_time":1.046526548},
{"learn":[1928.259178],"iteration":82,"passed_time":0.09459444966,"remaining_time":1.045097715},
{"learn":[1913.143001],"iteration":83,"passed_time":0.09574446949,"remaining_time":1.044070643},
{"learn":[1896.848527],"iteration":84,"passed_time":0.09689465962,"remaining_time":1.043042512},
{"learn":[1881.832131],"iteration":85,"passed_time":0.09802302047,"remaining_time":1.041779543},
{"learn":[1869.33616],"iteration":86,"passed_time":0.09910562897,"remaining_time":1.040039532},
{"learn":[1852.57493],"iteration":87,"passed_time":0.100308013,"remaining_time":1.039555772},
{"learn":[1839.157406],"iteration":88,"passed_time":0.1013646749,"remaining_time":1.037564256},
{"learn":[1825.568643],"iteration":89,"passed_time":0.1024301325,"remaining_time":1.035682451},
{"learn":[1810.319405],"iteration":90,"passed_time":0.1037975837,"remaining_time":1.036835204},
{"learn":[1798.779568],"iteration":91,"passed_time":0.1051566525,"remaining_time":1.03785044},
{"learn":[1786.513198],"iteration":92,"passed_time":0.1062181029,"remaining_time":1.035912036},
{"learn":[1773.94893],"iteration":93,"passed_time":0.1072648669,"remaining_time":1.033850738},
{"learn":[1759.507663],"iteration":94,"passed_time":0.1083201462,"remaining_time":1.031891919},
{"learn":[1746.035737],"iteration":95,"passed_time":0.1094791536,"remaining_time":1.030928696},
{"learn":[1733.613517],"iteration":96,"passed_time":0.1107613113,"remaining_time":1.031107877},
{"learn":[1724.698192],"iteration":97,"passed_time":0.1118443606,"remaining_time":1.029424625},
{"learn":[1713.524781],"iteration":98,"passed_time":0.1129103291,"remaining_time":1.027598046},
{"learn":[1701.243301],"iteration":99,"passed_time":0.1139602287,"remaining_time":1.025642059},
{"learn":[1688.706403],"iteration":100,"passed_time":0.1151708463,"remaining_time":1.025134562},
{"learn":[1678.588409],"iteration":101,"passed_time":0.1163865115,"remaining_time":1.024657719},
{"learn":[1671.449789],"iteration":102,"passed_time":0.1174588315,"remaining_time":1.022918173},
{"learn":[1659.255415],"iteration":103,"passed_time":0.1185375129,"remaining_time":1.021246265},
{"learn":[1648.892946],"iteration":104,"passed_time":0.1196091316,"remaining_time":1.019525455},
{"learn":[1638.824632],"iteration":105,"passed_time":0.1206841464,"remaining_time":1.017845537},
{"learn":[1625.246114],"iteration":106,"passed_time":0.1217511368,"remaining_time":1.016109955},
{"learn":[1614.835218],"iteration":107,"passed_time":0.1228669651,"remaining_time":1.014790119},
{"learn":[1603.872443],"iteration":108,"passed_time":0.1239549333,"remaining_time":1.013246289},
{"learn":[1592.584266],"iteration":109,"passed_time":0.1250431419,"remaining_time":1.011712693},
{"learn":[1586.898231],"iteration":110,"passed_time":0.126157748,"remaining_time":1.01039854},
{"learn":[1573.960967],"iteration":111,"passed_time":0.1272255799,"remaining_time":1.008717097},
{"learn":[1564.779624],"iteration":112,"passed_time":0.1282646801,"remaining_time":1.006820984},
{"learn":[1555.509909],"iteration":113,"passed_time":0.1293522274,"remaining_time":1.005316434},
{"learn":[1547.597806],"iteration":114,"passed_time":0.1304492018,"remaining_time":1.003891683},
{"learn":[1542.060862],"iteration":115,"passed_time":0.1315112934,"remaining_time":1.002206753},
{"learn":[1533.283007],"iteration":116,"passed_time":0.1325693076,"remaining_time":1.000501698},
{"learn":[1524.09364],"iteration":117,"passed_time":0.1336789251,"remaining_time":0.9991933213},
{"learn":[1514.854763],"iteration":118,"passed_time":0.1347368992,"remaining_time":0.9975059515},
{"learn":[1508.762126],"iteration":119,"passed_time":0.1358404154,"remaining_time":0.996163046},
{"learn":[1497.66289],"iteration":120,"passed_time":0.136895324,"remaining_time":0.9944709902},
{"learn":[1490.037892],"iteration":121,"passed_time":0.1375851055,"remaining_time":0.9901616609},
{"learn":[1481.507059],"iteration":122,"passed_time":0.1386485094,"remaining_time":0.9885751445},
{"learn":[1473.417503],"iteration":123,"passed_time":0.1397033279,"remaining_time":0.9869364134},
{"learn":[1467.443034],"iteration":124,"passed_time":0.1407758382,"remaining_time":0.9854308677},
{"learn":[1463.961984],"iteration":125,"passed_time":0.141851915,"remaining_time":0.9839569342},
{"learn":[1457.202832],"iteration":126,"passed_time":0.142947597,"remaining_time":0.9826240331},
{"learn":[1449.438812],"iteration":127,"passed_time":0.1440150182,"remaining_time":0.9811023114},
{"learn":[1441.309989],"iteration":128,"passed_time":0.1452970252,"remaining_time":0.9810365037},
{"learn":[1434.498925],"iteration":129,"passed_time":0.1465220203,"remaining_time":0.9805704439},
{"learn":[1428.211363],"iteration":130,"passed_time":0.1477676523,"remaining_time":0.9802296933},
{"learn":[1420.948565],"iteration":131,"passed_time":0.1490188338,"remaining_time":0.9799117254},
{"learn":[1411.130386],"iteration":132,"passed_time":0.1501883788,"remaining_time":0.979047552},
{"learn":[1405.835585],"iteration":133,"passed_time":0.1512904724,"remaining_time":0.9777429035},
{"learn":[1394.351105],"iteration":134,"passed_time":0.152354237,"remaining_time":0.9761956664},
{"learn":[1387.067728],"iteration":135,"passed_time":0.1534255451,"remaining_time":0.9747034631},
{"learn":[1379.331541],"iteration":136,"passed_time":0.1544971538,"remaining_time":0.9732192974},
{"learn":[1372.582548],"iteration":137,"passed_time":0.1556135024,"remaining_time":0.9720205727},
{"learn":[1368.748854],"iteration":138,"passed_time":0.1566931054,"remaining_time":0.970595423},
{"learn":[1361.090082],"iteration":139,"passed_time":0.1577682405,"remaining_time":0.9691477631},
{"learn":[1355.849113],"iteration":140,"passed_time":0.1589055575,"remaining_time":0.9680842118},
{"learn":[1353.021546],"iteration":141,"passed_time":0.1599870439,"remaining_time":0.9666822796},
{"learn":[1348.499442],"iteration":142,"passed_time":0.1611025016,"remaining_time":0.9654884185},
{"learn":[1342.972659],"iteration":143,"passed_time":0.1622546352,"remaining_time":0.9645136649},
{"learn":[1340.369547],"iteration":144,"passed_time":0.1633181393,"remaining_time":0.963013856},
{"learn":[1334.355184],"iteration":145,"passed_time":0.1643637813,"remaining_time":0.9614155426},
{"learn":[1330.900194],"iteration":146,"passed_time":0.165440389,"remaining_time":0.9600044341},
{"learn":[1326.320978],"iteration":147,"passed_time":0.1665374936,"remaining_time":0.9587158415},
{"learn":[1319.677791],"iteration":148,"passed_time":0.1676275555,"remaining_time":0.9573895955},
{"learn":[1312.322399],"iteration":149,"passed_time":0.1687245198,"remaining_time":0.9561056125},
{"learn":[1308.208566],"iteration":150,"passed_time":0.1692376434,"remaining_time":0.9515414518},
{"learn":[1302.440372],"iteration":151,"passed_time":0.1703137201,"remaining_time":0.9501712807},
{"learn":[1297.197478],"iteration":152,"passed_time":0.1714148219,"remaining_time":0.9489434912},
{"learn":[1290.193544],"iteration":153,"passed_time":0.1725004158,"remaining_time":0.9476321542},
{"learn":[1285.824262],"iteration":154,"passed_time":0.1735748896,"remaining_time":0.9462631081},
{"learn":[1275.305364],"iteration":155,"passed_time":0.1746525693,"remaining_time":0.9449151825},
{"learn":[1264.600978],"iteration":156,"passed_time":0.1757201507,"remaining_time":0.9435164781},
{"learn":[1258.175535],"iteration":157,"passed_time":0.1767868506,"remaining_time":0.9421172671},
{"learn":[1253.742932],"iteration":158,"passed_time":0.1778519476,"remaining_time":0.9407137605},
{"learn":[1245.902515],"iteration":159,"passed_time":0.1789204607,"remaining_time":0.9393324188},
{"learn":[1239.739039],"iteration":160,"passed_time":0.1799777937,"remaining_time":0.9378967015},
{"learn":[1232.78174],"iteration":161,"passed_time":0.1811043613,"remaining_time":0.9368237951},
{"learn":[1225.024098],"iteration":162,"passed_time":0.182167625,"remaining_time":0.9354251666},
{"learn":[1220.191889],"iteration":163,"passed_time":0.1832259699,"remaining_time":0.9340055537},
{"learn":[1217.982377],"iteration":164,"passed_time":0.1842712812,"remaining_time":0.9325243626},
{"learn":[1210.845683],"iteration":165,"passed_time":0.1853453744,"remaining_time":0.9311930257},
{"learn":[1208.597914],"iteration":166,"passed_time":0.1863876704,"remaining_time":0.9297061641},
{"learn":[1204.716907],"iteration":167,"passed_time":0.1875788242,"remaining_time":0.9289617962},
{"learn":[1199.530872],"iteration":168,"passed_time":0.1887012845,"remaining_time":0.9278743632},
{"learn":[1197.520859],"iteration":169,"passed_time":0.1897549709,"remaining_time":0.9264507403},
{"learn":[1193.466227],"iteration":170,"passed_time":0.1908430793,"remaining_time":0.9251983201},
{"learn":[1191.490901],"iteration":171,"passed_time":0.1918985089,"remaining_time":0.9237904963},
{"learn":[1187.849129],"iteration":172,"passed_time":0.1929604201,"remaining_time":0.9224177309},
{"learn":[1181.755184],"iteration":173,"passed_time":0.1940285526,"remaining_time":0.9210780715},
{"learn":[1179.396166],"iteration":174,"passed_time":0.1951235834,"remaining_time":0.9198683219},
{"learn":[1176.427422],"iteration":175,"passed_time":0.196176238,"remaining_time":0.9184614781},
{"learn":[1169.658324],"iteration":176,"passed_time":0.1972431082,"remaining_time":0.9171247348},
{"learn":[1165.534652],"iteration":177,"passed_time":0.1983061919,"remaining_time":0.9157735379},
{"learn":[1161.380996],"iteration":178,"passed_time":0.1993710885,"remaining_time":0.9144338754},
{"learn":[1155.747975],"iteration":179,"passed_time":0.2004257267,"remaining_time":0.9130505327},
{"learn":[1151.849368],"iteration":180,"passed_time":0.2014699661,"remaining_time":0.9116237694},
{"learn":[1148.33294],"iteration":181,"passed_time":0.2026069024,"remaining_time":0.9106178362},
{"learn":[1144.503373],"iteration":182,"passed_time":0.2036879481,"remaining_time":0.9093609487},
{"learn":[1139.668246],"iteration":183,"passed_time":0.204762973,"remaining_time":0.9080792714},
{"learn":[1137.576823],"iteration":184,"passed_time":0.2058149263,"remaining_time":0.9066981888},
{"learn":[1133.265987],"iteration":185,"passed_time":0.206865417,"remaining_time":0.9053142442},
{"learn":[1131.506571],"iteration":186,"passed_time":0.2079229904,"remaining_time":0.9039646589},
{"learn":[1128.159804],"iteration":187,"passed_time":0.2090022729,"remaining_time":0.9027119449},
{"learn":[1123.988728],"iteration":188,"passed_time":0.2100502992,"remaining_time":0.9013269453},
{"learn":[1121.602657],"iteration":189,"passed_time":0.2111059191,"remaining_time":0.8999778658},
{"learn":[1120.050863],"iteration":190,"passed_time":0.212144298,"remaining_time":0.898558833},
{"learn":[1115.684977],"iteration":191,"passed_time":0.2132093549,"remaining_time":0.8972560354},
{"learn":[1112.821223],"iteration":192,"passed_time":0.2143083029,"remaining_time":0.8960974114},
{"learn":[1108.051339],"iteration":193,"passed_time":0.215364584,"remaining_time":0.8947621375},
{"learn":[1103.326274],"iteration":194,"passed_time":0.2164641229,"remaining_time":0.8936083024},
{"learn":[1099.678916],"iteration":195,"passed_time":0.2175796904,"remaining_time":0.8925207709},
{"learn":[1097.758572],"iteration":196,"passed_time":0.2186504175,"remaining_time":0.8912501791},
{"learn":[1094.19877],"iteration":197,"passed_time":0.219706889,"remaining_time":0.8899238635},
{"learn":[1091.276658],"iteration":198,"passed_time":0.2207352298,"remaining_time":0.8884870306},
{"learn":[1089.742528],"iteration":199,"passed_time":0.2217852497,"remaining_time":0.8871409987},
{"learn":[1088.501026],"iteration":200,"passed_time":0.2228693008,"remaining_time":0.8859331906},
{"learn":[1086.422594],"iteration":201,"passed_time":0.2239280964,"remaining_time":0.8846268363},
{"learn":[1082.702745],"iteration":202,"passed_time":0.2249925322,"remaining_time":0.8833450649},
{"learn":[1077.44235],"iteration":203,"passed_time":0.2260586911,"remaining_time":0.8820721477},
{"learn":[1075.680367],"iteration":204,"passed_time":0.2271703319,"remaining_time":0.8809776284},
{"learn":[1071.230542],"iteration":205,"passed_time":0.2282275847,"remaining_time":0.879673312},
{"learn":[1068.176581],"iteration":206,"passed_time":0.2292805499,"remaining_time":0.8783549568},
{"learn":[1066.796186],"iteration":207,"passed_time":0.2303634689,"remaining_time":0.8771532086},
{"learn":[1061.364289],"iteration":208,"passed_time":0.2314440137,"remaining_time":0.8759436118},
{"learn":[1059.164348],"iteration":209,"passed_time":0.232514801,"remaining_time":0.8746985369},
{"learn":[1056.582573],"iteration":210,"passed_time":0.233584406,"remaining_time":0.8734506937},
{"learn":[1054.27004],"iteration":211,"passed_time":0.2346900761,"remaining_time":0.8723385846},
{"learn":[1052.99366],"iteration":212,"passed_time":0.2357657922,"remaining_time":0.8711158612},
{"learn":[1047.845628],"iteration":213,"passed_time":0.2368216826,"remaining_time":0.8698216939},
{"learn":[1045.666276],"iteration":214,"passed_time":0.2378604822,"remaining_time":0.8684673421},
{"learn":[1039.325311],"iteration":215,"passed_time":0.2389153107,"remaining_time":0.8671740908},
{"learn":[1034.800322],"iteration":216,"passed_time":0.2399720627,"remaining_time":0.8658899774},
{"learn":[1029.593986],"iteration":217,"passed_time":0.2410062741,"remaining_time":0.8645270933},
{"learn":[1027.739134],"iteration":218,"passed_time":0.2420419681,"remaining_time":0.8631724983},
{"learn":[1019.632518],"iteration":219,"passed_time":0.2431120541,"remaining_time":0.8619427373},
{"learn":[1017.506144],"iteration":220,"passed_time":0.2441459049,"remaining_time":0.8605866963},
{"learn":[1015.902833],"iteration":221,"passed_time":0.2454909184,"remaining_time":0.8603240294},
{"learn":[1013.709789],"iteration":222,"passed_time":0.2467123485,"remaining_time":0.8596210528},
{"learn":[1011.559652],"iteration":223,"passed_time":0.2479839326,"remaining_time":0.8590871952},
{"learn":[1008.00611],"iteration":224,"passed_time":0.2493522854,"remaining_time":0.8588800942},
{"learn":[1006.32814],"iteration":225,"passed_time":0.2507813209,"remaining_time":0.8588705414},
{"learn":[1003.713236],"iteration":226,"passed_time":0.2518838867,"remaining_time":0.8577367595},
{"learn":[1000.07037],"iteration":227,"passed_time":0.2529792067,"remaining_time":0.8565787173},
{"learn":[998.2021399],"iteration":228,"passed_time":0.2540659948,"remaining_time":0.8553924977},
{"learn":[996.0285473],"iteration":229,"passed_time":0.2551982077,"remaining_time":0.8543592171},
{"learn":[991.5040199],"iteration":230,"passed_time":0.2562945551,"remaining_time":0.8532056834},
{"learn":[989.2833812],"iteration":231,"passed_time":0.2573875882,"remaining_time":0.8520416713},
{"learn":[985.953912],"iteration":232,"passed_time":0.2585024589,"remaining_time":0.8509501545},
{"learn":[980.9999288],"iteration":233,"passed_time":0.2597313766,"remaining_time":0.8502317713},
{"learn":[977.3176643],"iteration":234,"passed_time":0.2608649068,"remaining_time":0.8491985263},
{"learn":[973.9939112],"iteration":235,"passed_time":0.2619548834,"remaining_time":0.8480234359},
{"learn":[971.6210712],"iteration":236,"passed_time":0.2630619238,"remaining_time":0.8469039993},
{"learn":[966.9713017],"iteration":237,"passed_time":0.264133833,"remaining_time":0.845672188},
{"learn":[962.9455585],"iteration":238,"passed_time":0.2653436404,"remaining_time":0.8448807966},
{"learn":[958.0701102],"iteration":239,"passed_time":0.2664127446,"remaining_time":0.843640358},
{"learn":[955.7559221],"iteration":240,"passed_time":0.267456363,"remaining_time":0.8423210767},
{"learn":[951.9036405],"iteration":241,"passed_time":0.2685157196,"remaining_time":0.8410533697},
{"learn":[946.679185],"iteration":242,"passed_time":0.2695864868,"remaining_time":0.8398229239},
{"learn":[944.929797],"iteration":243,"passed_time":0.2706335814,"remaining_time":0.8385204407},
{"learn":[939.9168751],"iteration":244,"passed_time":0.2719265499,"remaining_time":0.8379777354},
{"learn":[938.1663068],"iteration":245,"passed_time":0.2730090282,"remaining_time":0.8367837692},
{"learn":[936.6512015],"iteration":246,"passed_time":0.2742410611,"remaining_time":0.8360466357},
{"learn":[934.9233495],"iteration":247,"passed_time":0.2756515895,"remaining_time":0.8358467551},
{"learn":[933.2222858],"iteration":248,"passed_time":0.2767027914,"remaining_time":0.8345533991},
{"learn":[931.5791043],"iteration":249,"passed_time":0.2779155687,"remaining_time":0.8337467061},
{"learn":[929.36542],"iteration":250,"passed_time":0.2790038073,"remaining_time":0.8325651462},
{"learn":[926.7239558],"iteration":251,"passed_time":0.2800827693,"remaining_time":0.8313567913},
{"learn":[924.9605741],"iteration":252,"passed_time":0.2811229514,"remaining_time":0.8300349593},
{"learn":[922.374033],"iteration":253,"passed_time":0.2821757563,"remaining_time":0.828752418},
{"learn":[920.3056777],"iteration":254,"passed_time":0.2832093666,"remaining_time":0.8274156004},
{"learn":[918.6484273],"iteration":255,"passed_time":0.2844576633,"remaining_time":0.826705084},
{"learn":[916.9773805],"iteration":256,"passed_time":0.2855477252,"remaining_time":0.8255329177},
{"learn":[915.6824502],"iteration":257,"passed_time":0.2866020228,"remaining_time":0.8242585306},
{"learn":[911.5535703],"iteration":258,"passed_time":0.2876636435,"remaining_time":0.8230067947},
{"learn":[910.2096773],"iteration":259,"passed_time":0.2887810329,"remaining_time":0.8219152474},
{"learn":[906.2675294],"iteration":260,"passed_time":0.2898813833,"remaining_time":0.8207752577},
{"learn":[904.9478639],"iteration":261,"passed_time":0.2909702531,"remaining_time":0.8196032319},
{"learn":[901.7516434],"iteration":262,"passed_time":0.2920868227,"remaining_time":0.8185094613},
{"learn":[897.7428511],"iteration":263,"passed_time":0.2931795093,"remaining_time":0.8173489351},
{"learn":[894.6240722],"iteration":264,"passed_time":0.294258882,"remaining_time":0.8161519935},
{"learn":[890.1042305],"iteration":265,"passed_time":0.2953176276,"remaining_time":0.8148990174},
{"learn":[887.7317854],"iteration":266,"passed_time":0.2963660646,"remaining_time":0.813619196},
{"learn":[882.4740412],"iteration":267,"passed_time":0.2974200415,"remaining_time":0.8123562329},
{"learn":[880.5669948],"iteration":268,"passed_time":0.2984749001,"remaining_time":0.8110972192},
{"learn":[876.4274751],"iteration":269,"passed_time":0.2995166851,"remaining_time":0.8098043709},
{"learn":[872.6470677],"iteration":270,"passed_time":0.3005842265,"remaining_time":0.808582661},
{"learn":[870.826876],"iteration":271,"passed_time":0.3016331644,"remaining_time":0.807312293},
{"learn":[868.451747],"iteration":272,"passed_time":0.3026762117,"remaining_time":0.8060278605},
{"learn":[866.6414805],"iteration":273,"passed_time":0.3037950067,"remaining_time":0.8049458937},
{"learn":[864.0396632],"iteration":274,"passed_time":0.3048689697,"remaining_time":0.8037454655},
{"learn":[861.1737814],"iteration":275,"passed_time":0.3059173666,"remaining_time":0.8024788892},
{"learn":[855.2500954],"iteration":276,"passed_time":0.3069992738,"remaining_time":0.8013013537},
{"learn":[852.5648355],"iteration":277,"passed_time":0.3080679573,"remaining_time":0.8000901624},
{"learn":[849.7219365],"iteration":278,"passed_time":0.3091156329,"remaining_time":0.7988257037},
{"learn":[847.2654293],"iteration":279,"passed_time":0.3102017878,"remaining_time":0.79766174},
{"learn":[845.5766798],"iteration":280,"passed_time":0.3112565662,"remaining_time":0.7964180466},
{"learn":[841.6200181],"iteration":281,"passed_time":0.3122986518,"remaining_time":0.7951433758},
{"learn":[839.4262068],"iteration":282,"passed_time":0.3133669545,"remaining_time":0.7939367717},
{"learn":[836.3380549],"iteration":283,"passed_time":0.31443677,"remaining_time":0.7927349553},
{"learn":[834.5941189],"iteration":284,"passed_time":0.3154804584,"remaining_time":0.7914685186},
{"learn":[833.2796092],"iteration":285,"passed_time":0.3165374508,"remaining_time":0.7902368528},
{"learn":[827.9262651],"iteration":286,"passed_time":0.3175838542,"remaining_time":0.7889800977},
{"learn":[827.0248222],"iteration":287,"passed_time":0.3187388088,"remaining_time":0.7879931661},
{"learn":[824.8753429],"iteration":288,"passed_time":0.3198109785,"remaining_time":0.7868014038},
{"learn":[823.5596007],"iteration":289,"passed_time":0.3208955505,"remaining_time":0.7856408305},
{"learn":[821.1874228],"iteration":290,"passed_time":0.3219496277,"remaining_time":0.7844064811},
{"learn":[816.5356582],"iteration":291,"passed_time":0.3230089643,"remaining_time":0.7831861189},
{"learn":[811.791711],"iteration":292,"passed_time":0.3240704047,"remaining_time":0.7819719321},
{"learn":[805.8407839],"iteration":293,"passed_time":0.3251268561,"remaining_time":0.7807468041},
{"learn":[804.8521133],"iteration":294,"passed_time":0.3262019811,"remaining_time":0.7795674464},
{"learn":[802.1503988],"iteration":295,"passed_time":0.3272613278,"remaining_time":0.778351266},
{"learn":[797.5560377],"iteration":296,"passed_time":0.3283297908,"remaining_time":0.7771577203},
{"learn":[795.8210569],"iteration":297,"passed_time":0.3293847796,"remaining_time":0.7759332727},
{"learn":[790.8659844],"iteration":298,"passed_time":0.3304420926,"remaining_time":0.7747154077},
{"learn":[789.4064694],"iteration":299,"passed_time":0.3314834869,"remaining_time":0.7734614694},
{"learn":[788.4056394],"iteration":300,"passed_time":0.3325808848,"remaining_time":0.7723389982},
{"learn":[785.2771647],"iteration":301,"passed_time":0.3336922851,"remaining_time":0.7712490563},
{"learn":[783.137716],"iteration":302,"passed_time":0.3347520325,"remaining_time":0.7700401539},
{"learn":[782.3703233],"iteration":303,"passed_time":0.3358134528,"remaining_time":0.768836063},
{"learn":[781.3713256],"iteration":304,"passed_time":0.3368769169,"remaining_time":0.7676375647},
{"learn":[780.4106443],"iteration":305,"passed_time":0.3379308738,"remaining_time":0.766418387},
{"learn":[779.3118159],"iteration":306,"passed_time":0.3389836386,"remaining_time":0.7651975946},
{"learn":[777.2642738],"iteration":307,"passed_time":0.3400370646,"remaining_time":0.7639793788},
{"learn":[774.9994352],"iteration":308,"passed_time":0.3410775272,"remaining_time":0.7627332405},
{"learn":[772.6892752],"iteration":309,"passed_time":0.3421420932,"remaining_time":0.7615420785},
{"learn":[771.7715284],"iteration":310,"passed_time":0.3431949782,"remaining_time":0.7603258521},
{"learn":[769.7802516],"iteration":311,"passed_time":0.3442917022,"remaining_time":0.7592073432},
{"learn":[767.9213948],"iteration":312,"passed_time":0.3453511991,"remaining_time":0.7580072644},
{"learn":[767.0629293],"iteration":313,"passed_time":0.3464297603,"remaining_time":0.7568497311},
{"learn":[763.2506931],"iteration":314,"passed_time":0.3475145227,"remaining_time":0.7557061842},
{"learn":[761.0236056],"iteration":315,"passed_time":0.3485644423,"remaining_time":0.7544875903},
{"learn":[760.1433585],"iteration":316,"passed_time":0.3496159749,"remaining_time":0.7532735358},
{"learn":[756.0712172],"iteration":317,"passed_time":0.3506691304,"remaining_time":0.752063984},
{"learn":[753.9785519],"iteration":318,"passed_time":0.3517283568,"remaining_time":0.750868373},
{"learn":[752.3363898],"iteration":319,"passed_time":0.3527940248,"remaining_time":0.7496873027},
{"learn":[748.930684],"iteration":320,"passed_time":0.3538651426,"remaining_time":0.7485184793},
{"learn":[747.7261058],"iteration":321,"passed_time":0.3549228062,"remaining_time":0.7473219336},
{"learn":[745.9382928],"iteration":322,"passed_time":0.3559593218,"remaining_time":0.7460819221},
{"learn":[741.6498737],"iteration":323,"passed_time":0.3570340661,"remaining_time":0.7449229281},
{"learn":[740.0421988],"iteration":324,"passed_time":0.3580748694,"remaining_time":0.7436939595},
{"learn":[736.7973541],"iteration":325,"passed_time":0.3591461174,"remaining_time":0.7425290894},
{"learn":[733.1539911],"iteration":326,"passed_time":0.3602174256,"remaining_time":0.7413649157},
{"learn":[728.6433213],"iteration":327,"passed_time":0.361326091,"remaining_time":0.740277845},
{"learn":[727.5912122],"iteration":328,"passed_time":0.3624976797,"remaining_time":0.7393189758},
{"learn":[725.3105086],"iteration":329,"passed_time":0.3636348367,"remaining_time":0.7382889108},
{"learn":[723.443677],"iteration":330,"passed_time":0.3647215626,"remaining_time":0.73715627},
{"learn":[721.7420157],"iteration":331,"passed_time":0.3657843855,"remaining_time":0.7359758118},
{"learn":[719.2459879],"iteration":332,"passed_time":0.3668315602,"remaining_time":0.7347647167},
{"learn":[715.6812869],"iteration":333,"passed_time":0.3679028283,"remaining_time":0.7336026457},
{"learn":[713.5940947],"iteration":334,"passed_time":0.3689518063,"remaining_time":0.7323968692},
{"learn":[712.8518907],"iteration":335,"passed_time":0.3700030784,"remaining_time":0.7311965597},
{"learn":[711.3353987],"iteration":336,"passed_time":0.3710606719,"remaining_time":0.7300095711},
{"learn":[710.5610345],"iteration":337,"passed_time":0.3720956446,"remaining_time":0.7287790436},
{"learn":[709.8717679],"iteration":338,"passed_time":0.373164308,"remaining_time":0.7276153617},
{"learn":[706.5772896],"iteration":339,"passed_time":0.3742707394,"remaining_time":0.726525553},
{"learn":[705.8676888],"iteration":340,"passed_time":0.3753229933,"remaining_time":0.725330946},
{"learn":[704.0450265],"iteration":341,"passed_time":0.3764381403,"remaining_time":0.7242581765},
{"learn":[702.9236374],"iteration":342,"passed_time":0.3774790738,"remaining_time":0.7230430073},
{"learn":[699.9908143],"iteration":343,"passed_time":0.3785328004,"remaining_time":0.7218532472},
{"learn":[698.1448119],"iteration":344,"passed_time":0.3795977571,"remaining_time":0.7206855968},
{"learn":[696.7946544],"iteration":345,"passed_time":0.3806507122,"remaining_time":0.7194958549},
{"learn":[695.7608123],"iteration":346,"passed_time":0.3817049597,"remaining_time":0.7183093333},
{"learn":[693.0434905],"iteration":347,"passed_time":0.3827516235,"remaining_time":0.7171093635},
{"learn":[691.2134731],"iteration":348,"passed_time":0.3838277603,"remaining_time":0.7159652492},
{"learn":[689.5140859],"iteration":349,"passed_time":0.3849002106,"remaining_time":0.7148146768},
{"learn":[685.329922],"iteration":350,"passed_time":0.3859330194,"remaining_time":0.7135912524},
{"learn":[682.189651],"iteration":351,"passed_time":0.3870383288,"remaining_time":0.712502378},
{"learn":[680.1676794],"iteration":352,"passed_time":0.3881043274,"remaining_time":0.7113413593},
{"learn":[677.5999165],"iteration":353,"passed_time":0.389184762,"remaining_time":0.710207221},
{"learn":[673.717039],"iteration":354,"passed_time":0.3902559399,"remaining_time":0.7090565669},
{"learn":[672.1470626],"iteration":355,"passed_time":0.3913525222,"remaining_time":0.7079523154},
{"learn":[668.1048964],"iteration":356,"passed_time":0.3924313639,"remaining_time":0.706816154},
{"learn":[664.7529311],"iteration":357,"passed_time":0.3935025232,"remaining_time":0.705666536},
{"learn":[661.3091047],"iteration":358,"passed_time":0.3945611485,"remaining_time":0.7044949755},
{"learn":[659.1633941],"iteration":359,"passed_time":0.3956097558,"remaining_time":0.7033062326},
{"learn":[655.4729157],"iteration":360,"passed_time":0.3966629013,"remaining_time":0.702126299},
{"learn":[651.7568397],"iteration":361,"passed_time":0.3977309436,"remaining_time":0.7009733205},
{"learn":[650.5527398],"iteration":362,"passed_time":0.3987850708,"remaining_time":0.6997963915},
{"learn":[646.4712931],"iteration":363,"passed_time":0.3998398693,"remaining_time":0.6986213101},
{"learn":[642.2937832],"iteration":364,"passed_time":0.4009108969,"remaining_time":0.6974751221},
{"learn":[639.0453889],"iteration":365,"passed_time":0.4019583722,"remaining_time":0.6962885464},
{"learn":[636.7848859],"iteration":366,"passed_time":0.4030240402,"remaining_time":0.6951341075},
{"learn":[633.3046278],"iteration":367,"passed_time":0.4040927637,"remaining_time":0.6939853986},
{"learn":[630.6806144],"iteration":368,"passed_time":0.4053175688,"remaining_time":0.6931040269},
{"learn":[627.981333],"iteration":369,"passed_time":0.4064017802,"remaining_time":0.6919814096},
{"learn":[625.5669932],"iteration":370,"passed_time":0.4074661659,"remaining_time":0.6908253865},
{"learn":[620.9447056],"iteration":371,"passed_time":0.4085301409,"remaining_time":0.6896691626},
{"learn":[617.6141455],"iteration":372,"passed_time":0.4095873837,"remaining_time":0.6885021169},
{"learn":[614.943584],"iteration":373,"passed_time":0.4106368626,"remaining_time":0.6873226631},
{"learn":[612.0068767],"iteration":374,"passed_time":0.4116950872,"remaining_time":0.6861584787},
{"learn":[609.1491086],"iteration":375,"passed_time":0.4127500159,"remaining_time":0.6849893881},
{"learn":[607.7361304],"iteration":376,"passed_time":0.4138261027,"remaining_time":0.6838558673},
{"learn":[607.1760719],"iteration":377,"passed_time":0.4148907789,"remaining_time":0.6827038743},
{"learn":[605.0970056],"iteration":378,"passed_time":0.4159361103,"remaining_time":0.6815206451},
{"learn":[600.9987452],"iteration":379,"passed_time":0.4170059358,"remaining_time":0.6803781058},
{"learn":[600.4166952],"iteration":380,"passed_time":0.4180658334,"remaining_time":0.6792198186},
{"learn":[598.6553451],"iteration":381,"passed_time":0.4191011869,"remaining_time":0.678022339},
{"learn":[596.0097901],"iteration":382,"passed_time":0.4203022496,"remaining_time":0.677092658},
{"learn":[594.8305255],"iteration":383,"passed_time":0.4213509671,"remaining_time":0.6759171764},
{"learn":[591.2010104],"iteration":384,"passed_time":0.4224408988,"remaining_time":0.674808189},
{"learn":[588.9557654],"iteration":385,"passed_time":0.4234858596,"remaining_time":0.6736277662},
{"learn":[587.596638],"iteration":386,"passed_time":0.4245652022,"remaining_time":0.6725025037},
{"learn":[586.0089609],"iteration":387,"passed_time":0.4256444747,"remaining_time":0.6713773673},
{"learn":[582.622296],"iteration":388,"passed_time":0.4267095616,"remaining_time":0.6702301855},
{"learn":[581.1635269],"iteration":389,"passed_time":0.4277592509,"remaining_time":0.6690593411},
{"learn":[579.6505659],"iteration":390,"passed_time":0.4288147506,"remaining_time":0.6678981665},
{"learn":[577.2137656],"iteration":391,"passed_time":0.4298932718,"remaining_time":0.6667732378},
{"learn":[574.0104904],"iteration":392,"passed_time":0.4309755396,"remaining_time":0.6656543322},
{"learn":[572.6825933],"iteration":393,"passed_time":0.4320395246,"remaining_time":0.6645074922},
{"learn":[569.8333746],"iteration":394,"passed_time":0.4330786449,"remaining_time":0.6633229877},
{"learn":[566.4522007],"iteration":395,"passed_time":0.4342198481,"remaining_time":0.6622949199},
{"learn":[564.9314783],"iteration":396,"passed_time":0.4353396705,"remaining_time":0.6612338068},
{"learn":[564.3379193],"iteration":397,"passed_time":0.4366430495,"remaining_time":0.6604500396},
{"learn":[562.6469744],"iteration":398,"passed_time":0.4377959013,"remaining_time":0.659436934},
{"learn":[560.520165],"iteration":399,"passed_time":0.4389471364,"remaining_time":0.6584207046},
{"learn":[559.3440979],"iteration":400,"passed_time":0.4400296748,"remaining_time":0.657301185},
{"learn":[558.723729],"iteration":401,"passed_time":0.4410932089,"remaining_time":0.6561535795},
{"learn":[556.2338346],"iteration":402,"passed_time":0.4421589771,"remaining_time":0.6550097006},
{"learn":[555.2145738],"iteration":403,"passed_time":0.4432053104,"remaining_time":0.6538375371},
{"learn":[552.242973],"iteration":404,"passed_time":0.4442719601,"remaining_time":0.6526958427},
{"learn":[551.4284966],"iteration":405,"passed_time":0.4453216293,"remaining_time":0.6515296745},
{"learn":[550.1222868],"iteration":406,"passed_time":0.4464001705,"remaining_time":0.6504061453},
{"learn":[547.5988684],"iteration":407,"passed_time":0.4474522641,"remaining_time":0.6492444617},
{"learn":[546.0337883],"iteration":408,"passed_time":0.448577319,"remaining_time":0.6481887421},
{"learn":[541.0397987],"iteration":409,"passed_time":0.4496373869,"remaining_time":0.6470391666},
{"learn":[537.3221805],"iteration":410,"passed_time":0.4507073727,"remaining_time":0.6459042397},
{"learn":[534.5147907],"iteration":411,"passed_time":0.4517558398,"remaining_time":0.644738917},
{"learn":[533.3950297],"iteration":412,"passed_time":0.4528271169,"remaining_time":0.6436065801},
{"learn":[531.3618438],"iteration":413,"passed_time":0.4539115486,"remaining_time":0.6424931582},
{"learn":[528.3980605],"iteration":414,"passed_time":0.4549703242,"remaining_time":0.6413437101},
{"learn":[527.1340664],"iteration":415,"passed_time":0.4560292501,"remaining_time":0.6401949088},
{"learn":[525.3278762],"iteration":416,"passed_time":0.457078188,"remaining_time":0.6390325746},
{"learn":[523.8044977],"iteration":417,"passed_time":0.4581334473,"remaining_time":0.6378795845},
{"learn":[522.5679004],"iteration":418,"passed_time":0.4591872039,"remaining_time":0.6367249772},
{"learn":[520.0917311],"iteration":419,"passed_time":0.4602544748,"remaining_time":0.6355895128},
{"learn":[517.3278308],"iteration":420,"passed_time":0.4613320141,"remaining_time":0.6344684945},
{"learn":[516.2362235],"iteration":421,"passed_time":0.462537073,"remaining_time":0.6335223417},
{"learn":[514.9706983],"iteration":422,"passed_time":0.4636361698,"remaining_time":0.6324304255},
{"learn":[513.4089607],"iteration":423,"passed_time":0.4647384558,"remaining_time":0.6313428079},
{"learn":[512.2778079],"iteration":424,"passed_time":0.4658750308,"remaining_time":0.6303015122},
{"learn":[509.4536505],"iteration":425,"passed_time":0.4669865613,"remaining_time":0.6292260239},
{"learn":[506.1701355],"iteration":426,"passed_time":0.4681164435,"remaining_time":0.6281749933},
{"learn":[505.1773127],"iteration":427,"passed_time":0.4692201915,"remaining_time":0.6270886671},
{"learn":[503.0789974],"iteration":428,"passed_time":0.4703746593,"remaining_time":0.626069768},
{"learn":[501.6796145],"iteration":429,"passed_time":0.4715075839,"remaining_time":0.6250216809},
{"learn":[499.7179117],"iteration":430,"passed_time":0.4726052395,"remaining_time":0.6239266386},
{"learn":[498.0995086],"iteration":431,"passed_time":0.4736872369,"remaining_time":0.6228109966},
{"learn":[496.5389707],"iteration":432,"passed_time":0.4747453112,"remaining_time":0.6216641835},
{"learn":[493.4359713],"iteration":433,"passed_time":0.4758325781,"remaining_time":0.6205558507},
{"learn":[490.9150195],"iteration":434,"passed_time":0.4769555188,"remaining_time":0.6194939498},
{"learn":[488.886504],"iteration":435,"passed_time":0.478189925,"remaining_time":0.6185759581},
{"learn":[486.4428469],"iteration":436,"passed_time":0.4794737654,"remaining_time":0.6177202057},
{"learn":[485.7831349],"iteration":437,"passed_time":0.4805434105,"remaining_time":0.6165876637},
{"learn":[485.286253],"iteration":438,"passed_time":0.4816101505,"remaining_time":0.6154516957},
{"learn":[484.2533763],"iteration":439,"passed_time":0.4826970768,"remaining_time":0.614341734},
{"learn":[483.1297188],"iteration":440,"passed_time":0.4837632557,"remaining_time":0.6132055781},
{"learn":[482.679186],"iteration":441,"passed_time":0.4850984792,"remaining_time":0.6124093923},
{"learn":[481.084377],"iteration":442,"passed_time":0.4861783027,"remaining_time":0.6112896492},
{"learn":[479.0714118],"iteration":443,"passed_time":0.4872853552,"remaining_time":0.6102041835},
{"learn":[476.5101025],"iteration":444,"passed_time":0.4883499813,"remaining_time":0.609065707},
{"learn":[474.6292919],"iteration":445,"passed_time":0.489414377,"remaining_time":0.6079272755},
{"learn":[472.2199079],"iteration":446,"passed_time":0.4905791033,"remaining_time":0.6069132979},
{"learn":[470.1127085],"iteration":447,"passed_time":0.4917016637,"remaining_time":0.6058466928},
{"learn":[469.1864136],"iteration":448,"passed_time":0.4928228171,"remaining_time":0.6047781119},
{"learn":[468.1278243],"iteration":449,"passed_time":0.4939031916,"remaining_time":0.6036594564},
{"learn":[466.424419],"iteration":450,"passed_time":0.4949953273,"remaining_time":0.6025552875},
{"learn":[465.1484654],"iteration":451,"passed_time":0.4960597831,"remaining_time":0.6014176131},
{"learn":[464.3975737],"iteration":452,"passed_time":0.4971061564,"remaining_time":0.6002584272},
{"learn":[463.3004821],"iteration":453,"passed_time":0.4981509468,"remaining_time":0.5990978347},
{"learn":[462.3532266],"iteration":454,"passed_time":0.4992582342,"remaining_time":0.5980126102},
{"learn":[459.4371762],"iteration":455,"passed_time":0.5003316963,"remaining_time":0.5968869359},
{"learn":[458.570099],"iteration":456,"passed_time":0.5013918143,"remaining_time":0.5957456349},
{"learn":[457.1317973],"iteration":457,"passed_time":0.502449518,"remaining_time":0.5946018313},
{"learn":[456.3639736],"iteration":458,"passed_time":0.5035020423,"remaining_time":0.5934522982},
{"learn":[454.3063486],"iteration":459,"passed_time":0.5045760053,"remaining_time":0.592328354},
{"learn":[453.715047],"iteration":460,"passed_time":0.5056564094,"remaining_time":0.5912121577},
{"learn":[452.6818588],"iteration":461,"passed_time":0.5067590039,"remaining_time":0.5901219569},
{"learn":[449.8020912],"iteration":462,"passed_time":0.507815846,"remaining_time":0.5889786379},
{"learn":[448.8575668],"iteration":463,"passed_time":0.5088827863,"remaining_time":0.5878473566},
{"learn":[448.2370419],"iteration":464,"passed_time":0.5099669777,"remaining_time":0.5867362001},
{"learn":[446.730661],"iteration":465,"passed_time":0.5110198226,"remaining_time":0.5855892388},
{"learn":[446.3415773],"iteration":466,"passed_time":0.5120836774,"remaining_time":0.5844552463},
{"learn":[445.7695707],"iteration":467,"passed_time":0.5131353402,"remaining_time":0.5833076944},
{"learn":[443.905579],"iteration":468,"passed_time":0.5142130699,"remaining_time":0.5821900642},
{"learn":[442.3626883],"iteration":469,"passed_time":0.5152749411,"remaining_time":0.5810547208},
{"learn":[440.7837324],"iteration":470,"passed_time":0.5163475917,"remaining_time":0.5799317962},
{"learn":[438.6759861],"iteration":471,"passed_time":0.5174202222,"remaining_time":0.5788090621},
{"learn":[436.8103166],"iteration":472,"passed_time":0.5184708632,"remaining_time":0.5776620399},
{"learn":[435.6750119],"iteration":473,"passed_time":0.5195784352,"remaining_time":0.5765786011},
{"learn":[433.6895412],"iteration":474,"passed_time":0.5206546021,"remaining_time":0.5754603497},
{"learn":[431.689376],"iteration":475,"passed_time":0.5217205006,"remaining_time":0.5743309712},
{"learn":[430.6061767],"iteration":476,"passed_time":0.5228195103,"remaining_time":0.5732381633},
{"learn":[429.1647466],"iteration":477,"passed_time":0.5238953867,"remaining_time":0.5721200666},
{"learn":[428.7692166],"iteration":478,"passed_time":0.5249622869,"remaining_time":0.5709923831},
{"learn":[428.3646892],"iteration":479,"passed_time":0.5260219742,"remaining_time":0.5698571387},
{"learn":[426.5750094],"iteration":480,"passed_time":0.5270851777,"remaining_time":0.5687260026},
{"learn":[424.3717338],"iteration":481,"passed_time":0.5281330537,"remaining_time":0.567578676},
{"learn":[422.6050251],"iteration":482,"passed_time":0.529172745,"remaining_time":0.5664230003},
{"learn":[420.7835995],"iteration":483,"passed_time":0.5302386134,"remaining_time":0.5652957118},
{"learn":[419.8929829],"iteration":484,"passed_time":0.5313022177,"remaining_time":0.5641662724},
{"learn":[418.1078269],"iteration":485,"passed_time":0.5323910674,"remaining_time":0.5630638038},
{"learn":[417.820716],"iteration":486,"passed_time":0.5334389334,"remaining_time":0.5619182193},
{"learn":[417.4713632],"iteration":487,"passed_time":0.5345977946,"remaining_time":0.5608894894},
{"learn":[415.8904682],"iteration":488,"passed_time":0.5356938173,"remaining_time":0.5597945616},
{"learn":[413.9423622],"iteration":489,"passed_time":0.5367497578,"remaining_time":0.5586579112},
{"learn":[413.5741923],"iteration":490,"passed_time":0.5377942877,"remaining_time":0.5575097606},
{"learn":[412.2879307],"iteration":491,"passed_time":0.538847323,"remaining_time":0.5563708132},
{"learn":[410.3135913],"iteration":492,"passed_time":0.5399153252,"remaining_time":0.5552476063},
{"learn":[408.3486956],"iteration":493,"passed_time":0.5409751728,"remaining_time":0.5541162701},
{"learn":[406.0178373],"iteration":494,"passed_time":0.5420215761,"remaining_time":0.5529715069},
{"learn":[405.12663],"iteration":495,"passed_time":0.5430770157,"remaining_time":0.5518363224},
{"learn":[403.8685309],"iteration":496,"passed_time":0.5441518602,"remaining_time":0.550721098},
{"learn":[402.7827948],"iteration":497,"passed_time":0.5452209845,"remaining_time":0.5496002695},
{"learn":[402.2393243],"iteration":498,"passed_time":0.5462916916,"remaining_time":0.5484812374},
{"learn":[401.2249659],"iteration":499,"passed_time":0.5473644824,"remaining_time":0.5473644824},
{"learn":[400.4301768],"iteration":500,"passed_time":0.5484219957,"remaining_time":0.5462326864},
{"learn":[399.4604371],"iteration":501,"passed_time":0.5495895471,"remaining_time":0.5452103475},
{"learn":[398.2157152],"iteration":502,"passed_time":0.5506570785,"remaining_time":0.5440886044},
{"learn":[397.6801859],"iteration":503,"passed_time":0.5517304003,"remaining_time":0.5429727749},
{"learn":[395.602014],"iteration":504,"passed_time":0.5528038423,"remaining_time":0.5418572315},
{"learn":[393.4295373],"iteration":505,"passed_time":0.5538545834,"remaining_time":0.5407196921},
{"learn":[391.9184919],"iteration":506,"passed_time":0.5549199709,"remaining_time":0.539596737},
{"learn":[391.422458],"iteration":507,"passed_time":0.5559772538,"remaining_time":0.5384661592},
{"learn":[389.4992376],"iteration":508,"passed_time":0.5570309303,"remaining_time":0.5373323905},
{"learn":[388.724925],"iteration":509,"passed_time":0.5580842561,"remaining_time":0.536198599},
{"learn":[387.1581567],"iteration":510,"passed_time":0.559194324,"remaining_time":0.5351194216},
{"learn":[385.757448],"iteration":511,"passed_time":0.5602725045,"remaining_time":0.5340097309},
{"learn":[385.3383786],"iteration":512,"passed_time":0.5613397253,"remaining_time":0.5328897587},
{"learn":[384.3671143],"iteration":513,"passed_time":0.5624133705,"remaining_time":0.5317760662},
{"learn":[382.4818949],"iteration":514,"passed_time":0.5635135323,"remaining_time":0.5306875013},
{"learn":[381.8726626],"iteration":515,"passed_time":0.5645777577,"remaining_time":0.5295651836},
{"learn":[379.6920747],"iteration":516,"passed_time":0.5656285089,"remaining_time":0.5284305025},
{"learn":[378.1686157],"iteration":517,"passed_time":0.5666622694,"remaining_time":0.5272803357},
{"learn":[377.336081],"iteration":518,"passed_time":0.5677175387,"remaining_time":0.5261505513},
{"learn":[375.1518045],"iteration":519,"passed_time":0.5687699729,"remaining_time":0.5250184365},
{"learn":[374.2227638],"iteration":520,"passed_time":0.5698309024,"remaining_time":0.5238944381},
{"learn":[371.4295495],"iteration":521,"passed_time":0.5708914612,"remaining_time":0.5227703419},
{"learn":[370.9733131],"iteration":522,"passed_time":0.571958662,"remaining_time":0.5216525464},
{"learn":[369.4625339],"iteration":523,"passed_time":0.5730683292,"remaining_time":0.5205735204},
{"learn":[367.4440877],"iteration":524,"passed_time":0.5741423823,"remaining_time":0.5194621554},
{"learn":[364.914866],"iteration":525,"passed_time":0.5751917209,"remaining_time":0.5183286611},
{"learn":[364.5184949],"iteration":526,"passed_time":0.5762350087,"remaining_time":0.5171900552},
{"learn":[364.0196932],"iteration":527,"passed_time":0.5772835959,"remaining_time":0.5160565479},
{"learn":[361.9671328],"iteration":528,"passed_time":0.5784026998,"remaining_time":0.5149861467},
{"learn":[360.7296167],"iteration":529,"passed_time":0.579476252,"remaining_time":0.5138751668},
{"learn":[359.8053364],"iteration":530,"passed_time":0.5805354584,"remaining_time":0.5127516572},
{"learn":[358.2113933],"iteration":531,"passed_time":0.5815823426,"remaining_time":0.5116175495},
{"learn":[357.1322356],"iteration":532,"passed_time":0.5826182069,"remaining_time":0.5104741138},
{"learn":[355.9075457],"iteration":533,"passed_time":0.5836717131,"remaining_time":0.5093464762},
{"learn":[354.1031974],"iteration":534,"passed_time":0.5847328229,"remaining_time":0.5082257245},
{"learn":[352.42723],"iteration":535,"passed_time":0.58578687,"remaining_time":0.5070990815},
{"learn":[351.8381396],"iteration":536,"passed_time":0.5868482202,"remaining_time":0.5059790055},
{"learn":[349.8564592],"iteration":537,"passed_time":0.5879017363,"remaining_time":0.5048524204},
{"learn":[349.0198448],"iteration":538,"passed_time":0.5889576668,"remaining_time":0.5037281714},
{"learn":[347.8366573],"iteration":539,"passed_time":0.5900214214,"remaining_time":0.5026108404},
{"learn":[346.8854829],"iteration":540,"passed_time":0.5910562739,"remaining_time":0.5014691862},
{"learn":[346.2852633],"iteration":541,"passed_time":0.5921260597,"remaining_time":0.5003574453},
{"learn":[344.8233277],"iteration":542,"passed_time":0.5932173739,"remaining_time":0.4992639776},
{"learn":[343.5106046],"iteration":543,"passed_time":0.5942733945,"remaining_time":0.4981409336},
{"learn":[341.8230519],"iteration":544,"passed_time":0.5953494112,"remaining_time":0.4970348295},
{"learn":[340.9638181],"iteration":545,"passed_time":0.5964107314,"remaining_time":0.4959166154},
{"learn":[339.9518758],"iteration":546,"passed_time":0.5974575554,"remaining_time":0.4947866044},
{"learn":[338.0661105],"iteration":547,"passed_time":0.5985296851,"remaining_time":0.4936777695},
{"learn":[336.4888121],"iteration":548,"passed_time":0.599598098,"remaining_time":0.492566015},
{"learn":[335.5156359],"iteration":549,"passed_time":0.6006667815,"remaining_time":0.4914546394},
{"learn":[333.7940435],"iteration":550,"passed_time":0.6017421169,"remaining_time":0.4903488394},
{"learn":[332.2242285],"iteration":551,"passed_time":0.6028165807,"remaining_time":0.4892424423},
{"learn":[330.8002068],"iteration":552,"passed_time":0.6038930682,"remaining_time":0.4881377966},
{"learn":[330.0581302],"iteration":553,"passed_time":0.6049461135,"remaining_time":0.4870143802},
{"learn":[329.3385163],"iteration":554,"passed_time":0.6060018537,"remaining_time":0.4858933782},
{"learn":[327.4913103],"iteration":555,"passed_time":0.6075147255,"remaining_time":0.4851376585},
{"learn":[326.2839915],"iteration":556,"passed_time":0.6086059996,"remaining_time":0.4840439099},
{"learn":[325.0058855],"iteration":557,"passed_time":0.6096737814,"remaining_time":0.4829315616},
{"learn":[322.9525721],"iteration":558,"passed_time":0.6107198241,"remaining_time":0.4818022226},
{"learn":[321.99419],"iteration":559,"passed_time":0.6117750133,"remaining_time":0.4806803676},
{"learn":[320.6959685],"iteration":560,"passed_time":0.6129157077,"remaining_time":0.4796256608},
{"learn":[319.7365462],"iteration":561,"passed_time":0.6140026841,"remaining_time":0.4785287822},
{"learn":[319.217626],"iteration":562,"passed_time":0.6150309648,"remaining_time":0.4773863794},
{"learn":[317.3638793],"iteration":563,"passed_time":0.6160908223,"remaining_time":0.4762687917},
{"learn":[316.0513908],"iteration":564,"passed_time":0.6171576024,"remaining_time":0.4751567381},
{"learn":[315.3036364],"iteration":565,"passed_time":0.6182097661,"remaining_time":0.4740336369},
{"learn":[313.8623121],"iteration":566,"passed_time":0.619280924,"remaining_time":0.4729252911},
{"learn":[312.0597658],"iteration":567,"passed_time":0.620324402,"remaining_time":0.4717960241},
{"learn":[311.6755412],"iteration":568,"passed_time":0.6219824662,"remaining_time":0.4711325887},
{"learn":[310.8257192],"iteration":569,"passed_time":0.6230439467,"remaining_time":0.4700156089},
{"learn":[309.1565618],"iteration":570,"passed_time":0.6240970421,"remaining_time":0.4688925238},
{"learn":[307.7029353],"iteration":571,"passed_time":0.6251617083,"remaining_time":0.4677783412},
{"learn":[306.3908228],"iteration":572,"passed_time":0.6262226578,"remaining_time":0.4666615618},
{"learn":[304.6760682],"iteration":573,"passed_time":0.6273066288,"remaining_time":0.4655620625},
{"learn":[303.5260604],"iteration":574,"passed_time":0.6283756629,"remaining_time":0.4644515769},
{"learn":[302.5788671],"iteration":575,"passed_time":0.6294464902,"remaining_time":0.4633425553},
{"learn":[301.1675292],"iteration":576,"passed_time":0.6305202227,"remaining_time":0.4622357958},
{"learn":[300.1158723],"iteration":577,"passed_time":0.6315895373,"remaining_time":0.4611259251},
{"learn":[298.5581477],"iteration":578,"passed_time":0.6326592325,"remaining_time":0.4600164713},
{"learn":[297.9609128],"iteration":579,"passed_time":0.6337187996,"remaining_time":0.4588998204},
{"learn":[296.4468905],"iteration":580,"passed_time":0.6348124687,"remaining_time":0.4578079593},
{"learn":[295.9593591],"iteration":581,"passed_time":0.6358795492,"remaining_time":0.4566969958},
{"learn":[294.0571663],"iteration":582,"passed_time":0.636927305,"remaining_time":0.4555723605},
{"learn":[292.6639267],"iteration":583,"passed_time":0.6380097231,"remaining_time":0.4544726795},
{"learn":[291.6902337],"iteration":584,"passed_time":0.6390822134,"remaining_time":0.4533660147},
{"learn":[291.1373895],"iteration":585,"passed_time":0.6401134395,"remaining_time":0.4522303139},
{"learn":[290.9389487],"iteration":586,"passed_time":0.6411690093,"remaining_time":0.4511120968},
{"learn":[289.9088179],"iteration":587,"passed_time":0.6422390251,"remaining_time":0.4500042149},
{"learn":[288.5714527],"iteration":588,"passed_time":0.6432976204,"remaining_time":0.4488884923},
{"learn":[287.9920951],"iteration":589,"passed_time":0.6443421103,"remaining_time":0.4477631614},
{"learn":[287.0685734],"iteration":590,"passed_time":0.6454031199,"remaining_time":0.4466495365},
{"learn":[285.9893815],"iteration":591,"passed_time":0.6464890644,"remaining_time":0.4455532741},
{"learn":[285.5013191],"iteration":592,"passed_time":0.6475363093,"remaining_time":0.4444304855},
{"learn":[283.6919606],"iteration":593,"passed_time":0.6485996331,"remaining_time":0.4433189411},
{"learn":[283.2875407],"iteration":594,"passed_time":0.6496442332,"remaining_time":0.4421948142},
{"learn":[282.705433],"iteration":595,"passed_time":0.6512102576,"remaining_time":0.4414244028},
{"learn":[280.8705714],"iteration":596,"passed_time":0.6525330232,"remaining_time":0.4404871161},
{"learn":[278.9462917],"iteration":597,"passed_time":0.6538930282,"remaining_time":0.4395735741},
{"learn":[277.3667733],"iteration":598,"passed_time":0.6550340618,"remaining_time":0.4385119512},
{"learn":[275.9401325],"iteration":599,"passed_time":0.6562227513,"remaining_time":0.4374818342},
{"learn":[275.3525308],"iteration":600,"passed_time":0.6573342718,"remaining_time":0.4363999575},
{"learn":[274.2172324],"iteration":601,"passed_time":0.6584037467,"remaining_time":0.4352901847},
{"learn":[273.1454496],"iteration":602,"passed_time":0.6595941664,"remaining_time":0.4342601726},
{"learn":[272.2273976],"iteration":603,"passed_time":0.6606524612,"remaining_time":0.4331430044},
{"learn":[271.9563482],"iteration":604,"passed_time":0.6617289487,"remaining_time":0.4320379086},
{"learn":[270.523289],"iteration":605,"passed_time":0.6627974818,"remaining_time":0.4309277357},
{"learn":[269.4155328],"iteration":606,"passed_time":0.6638937052,"remaining_time":0.4298356279},
{"learn":[268.3822415],"iteration":607,"passed_time":0.6650008078,"remaining_time":0.4287505208},
{"learn":[266.9157367],"iteration":608,"passed_time":0.6664348529,"remaining_time":0.4278752504},
{"learn":[266.4445612],"iteration":609,"passed_time":0.6675308055,"remaining_time":0.4267819904},
{"learn":[265.6008547],"iteration":610,"passed_time":0.6686018532,"remaining_time":0.4256728656},
{"learn":[265.120143],"iteration":611,"passed_time":0.6696619812,"remaining_time":0.4245569423},
{"learn":[263.7820577],"iteration":612,"passed_time":0.6707005204,"remaining_time":0.4234275716},
{"learn":[262.9243177],"iteration":613,"passed_time":0.6718614799,"remaining_time":0.4223754581},
{"learn":[261.1231025],"iteration":614,"passed_time":0.6730035354,"remaining_time":0.4213111563},
{"learn":[259.6382428],"iteration":615,"passed_time":0.6740744529,"remaining_time":0.4202022563},
{"learn":[258.9858208],"iteration":616,"passed_time":0.6751447091,"remaining_time":0.419093069},
{"learn":[257.6179567],"iteration":617,"passed_time":0.6761752139,"remaining_time":0.4179594364},
{"learn":[256.8899284],"iteration":618,"passed_time":0.6772372153,"remaining_time":0.4168455235},
{"learn":[255.4967428],"iteration":619,"passed_time":0.6783330376,"remaining_time":0.4157525069},
{"learn":[254.4052147],"iteration":620,"passed_time":0.6795329627,"remaining_time":0.4147230159},
{"learn":[253.906998],"iteration":621,"passed_time":0.6806226339,"remaining_time":0.4136259737},
{"learn":[253.4435694],"iteration":622,"passed_time":0.6817015558,"remaining_time":0.4125224503},
{"learn":[252.95893],"iteration":623,"passed_time":0.6827840842,"remaining_time":0.4114211789},
{"learn":[251.878772],"iteration":624,"passed_time":0.6838434809,"remaining_time":0.4103060885},
{"learn":[251.255638],"iteration":625,"passed_time":0.684902567,"remaining_time":0.4091909905},
{"learn":[250.046226],"iteration":626,"passed_time":0.6859652697,"remaining_time":0.4080782227},
{"learn":[249.779545],"iteration":627,"passed_time":0.6870050011,"remaining_time":0.406952007},
{"learn":[249.6042643],"iteration":628,"passed_time":0.6880354056,"remaining_time":0.4058205651},
{"learn":[249.0860716],"iteration":629,"passed_time":0.6890794848,"remaining_time":0.4046974752},
{"learn":[248.7691773],"iteration":630,"passed_time":0.6901442211,"remaining_time":0.4035867157},
{"learn":[247.707954],"iteration":631,"passed_time":0.6912128645,"remaining_time":0.4024783768},
{"learn":[246.8696851],"iteration":632,"passed_time":0.6923863866,"remaining_time":0.4014309698},
{"learn":[246.2143924],"iteration":633,"passed_time":0.6934830908,"remaining_time":0.400338819},
{"learn":[245.0750729],"iteration":634,"passed_time":0.694557745,"remaining_time":0.3992339794},
{"learn":[243.8143998],"iteration":635,"passed_time":0.6956082758,"remaining_time":0.3981154283},
{"learn":[242.9252981],"iteration":636,"passed_time":0.6966414453,"remaining_time":0.3969871972},
{"learn":[241.672377],"iteration":637,"passed_time":0.6977574339,"remaining_time":0.3959062556},
{"learn":[241.3060003],"iteration":638,"passed_time":0.6988057607,"remaining_time":0.394786979},
{"learn":[239.8272826],"iteration":639,"passed_time":0.699869365,"remaining_time":0.3936765178},
{"learn":[238.6004673],"iteration":640,"passed_time":0.7009107793,"remaining_time":0.392553775},
{"learn":[238.3767373],"iteration":641,"passed_time":0.7019716888,"remaining_time":0.3914421567},
{"learn":[238.0477327],"iteration":642,"passed_time":0.7029810955,"remaining_time":0.3903021012},
{"learn":[237.8110821],"iteration":643,"passed_time":0.704032037,"remaining_time":0.3891854118},
{"learn":[236.1701588],"iteration":644,"passed_time":0.7051030747,"remaining_time":0.3880799868},
{"learn":[235.7824896],"iteration":645,"passed_time":0.7061607583,"remaining_time":0.3869673505},
{"learn":[234.4371719],"iteration":646,"passed_time":0.7072410223,"remaining_time":0.3858672038},
{"learn":[233.586054],"iteration":647,"passed_time":0.7084093551,"remaining_time":0.3848149583},
{"learn":[232.1746155],"iteration":648,"passed_time":0.7094745923,"remaining_time":0.3837065977},
{"learn":[231.9601495],"iteration":649,"passed_time":0.7105294909,"remaining_time":0.3825928028},
{"learn":[230.7055379],"iteration":650,"passed_time":0.7116251229,"remaining_time":0.3815010259},
{"learn":[229.959862],"iteration":651,"passed_time":0.7126779478,"remaining_time":0.3803863893},
{"learn":[228.9942889],"iteration":652,"passed_time":0.7137607667,"remaining_time":0.3792878806},
{"learn":[227.582597],"iteration":653,"passed_time":0.7148338079,"remaining_time":0.378184247},
{"learn":[225.9660434],"iteration":654,"passed_time":0.7158707342,"remaining_time":0.3770616844},
{"learn":[224.7925396],"iteration":655,"passed_time":0.716931854,"remaining_time":0.3759520698},
{"learn":[224.5845588],"iteration":656,"passed_time":0.7179494555,"remaining_time":0.3748198832},
{"learn":[223.5148323],"iteration":657,"passed_time":0.7190242099,"remaining_time":0.3737177504},
{"learn":[222.5828555],"iteration":658,"passed_time":0.7200811121,"remaining_time":0.3726064632},
{"learn":[221.6478158],"iteration":659,"passed_time":0.721166115,"remaining_time":0.3715098168},
{"learn":[220.7050421],"iteration":660,"passed_time":0.7224023299,"remaining_time":0.3704907562},
{"learn":[220.5249007],"iteration":661,"passed_time":0.7234869921,"remaining_time":0.3693936606},
{"learn":[219.9151002],"iteration":662,"passed_time":0.7245629086,"remaining_time":0.3682921571},
{"learn":[218.7304687],"iteration":663,"passed_time":0.725622135,"remaining_time":0.3671822852},
{"learn":[217.9857322],"iteration":664,"passed_time":0.726693934,"remaining_time":0.3660788991},
{"learn":[216.9364166],"iteration":665,"passed_time":0.7277561859,"remaining_time":0.36497082},
{"learn":[216.0870079],"iteration":666,"passed_time":0.7288138595,"remaining_time":0.3638605925},
{"learn":[215.8874796],"iteration":667,"passed_time":0.72987532,"remaining_time":0.3627524045},
{"learn":[214.5372808],"iteration":668,"passed_time":0.7309497638,"remaining_time":0.36165078},
{"learn":[214.3345393],"iteration":669,"passed_time":0.7320091004,"remaining_time":0.3605417957},
{"learn":[213.7400657],"iteration":670,"passed_time":0.7330676957,"remaining_time":0.3594325959},
{"learn":[212.6523336],"iteration":671,"passed_time":0.7341160926,"remaining_time":0.358318569},
{"learn":[212.0894037],"iteration":672,"passed_time":0.7351785148,"remaining_time":0.3572115518},
{"learn":[211.5415663],"iteration":673,"passed_time":0.7363291657,"remaining_time":0.3561473413},
{"learn":[211.3471921],"iteration":674,"passed_time":0.7373886426,"remaining_time":0.3550389761},
{"learn":[210.6393386],"iteration":675,"passed_time":0.7384633068,"remaining_time":0.3539380346},
{"learn":[209.5736289],"iteration":676,"passed_time":0.7395265304,"remaining_time":0.3528317124},
{"learn":[208.5912107],"iteration":677,"passed_time":0.7405933205,"remaining_time":0.3517272112},
{"learn":[207.4496718],"iteration":678,"passed_time":0.7416765801,"remaining_time":0.3506306071},
{"learn":[206.4629505],"iteration":679,"passed_time":0.7427242357,"remaining_time":0.3495172874},
{"learn":[205.9341326],"iteration":680,"passed_time":0.7437931696,"remaining_time":0.3484141279},
{"learn":[205.0460906],"iteration":681,"passed_time":0.7448723319,"remaining_time":0.347315838},
{"learn":[204.8566208],"iteration":682,"passed_time":0.7459280921,"remaining_time":0.3462067426},
{"learn":[204.1571191],"iteration":683,"passed_time":0.7470066834,"remaining_time":0.3451083508},
{"learn":[203.0443423],"iteration":684,"passed_time":0.7480770999,"remaining_time":0.3440062576},
{"learn":[201.8926949],"iteration":685,"passed_time":0.749130606,"remaining_time":0.3428965165},
{"learn":[201.5478669],"iteration":686,"passed_time":0.7502884842,"remaining_time":0.3418344913},
{"learn":[201.2050238],"iteration":687,"passed_time":0.7514495238,"remaining_time":0.3407736213},
{"learn":[200.3602799],"iteration":688,"passed_time":0.7525110945,"remaining_time":0.3396675622},
{"learn":[199.1413767],"iteration":689,"passed_time":0.7535686879,"remaining_time":0.3385598453},
{"learn":[198.4173253],"iteration":690,"passed_time":0.754599914,"remaining_time":0.3374404825},
{"learn":[197.4300363],"iteration":691,"passed_time":0.7556488118,"remaining_time":0.3363292399},
{"learn":[196.8465132],"iteration":692,"passed_time":0.7566887234,"remaining_time":0.3352141964},
{"learn":[196.1747274],"iteration":693,"passed_time":0.7577436321,"remaining_time":0.3341059819},
{"learn":[195.3325189],"iteration":694,"passed_time":0.7587977193,"remaining_time":0.3329975602},
{"learn":[194.2058954],"iteration":695,"passed_time":0.7598501234,"remaining_time":0.3318885596},
{"learn":[193.7140515],"iteration":696,"passed_time":0.7609157313,"remaining_time":0.3307854614},
{"learn":[192.8051386],"iteration":697,"passed_time":0.7619763903,"remaining_time":0.3296803293},
{"learn":[192.6301479],"iteration":698,"passed_time":0.7630333627,"remaining_time":0.328573737},
{"learn":[191.6973941],"iteration":699,"passed_time":0.7641933563,"remaining_time":0.3275114384},
{"learn":[191.5184005],"iteration":700,"passed_time":0.7652817152,"remaining_time":0.3264183065},
{"learn":[191.2053163],"iteration":701,"passed_time":0.7663267761,"remaining_time":0.3253068081},
{"learn":[190.3734948],"iteration":702,"passed_time":0.7673872147,"remaining_time":0.3242019954},
{"learn":[189.9206858],"iteration":703,"passed_time":0.7684645136,"remaining_time":0.3231043978},
{"learn":[188.8778237],"iteration":704,"passed_time":0.7695166573,"remaining_time":0.3219963318},
{"learn":[188.03912],"iteration":705,"passed_time":0.7705708647,"remaining_time":0.3208892836},
{"learn":[187.8661398],"iteration":706,"passed_time":0.7716157853,"remaining_time":0.3197785362},
{"learn":[187.2103866],"iteration":707,"passed_time":0.7726893977,"remaining_time":0.3186798081},
{"learn":[186.879634],"iteration":708,"passed_time":0.7737453081,"remaining_time":0.3175738853},
{"learn":[185.6191436],"iteration":709,"passed_time":0.774800377,"remaining_time":0.3164677596},
{"learn":[185.4185016],"iteration":710,"passed_time":0.7758445664,"remaining_time":0.3153573554},
{"learn":[184.9978368],"iteration":711,"passed_time":0.7768983029,"remaining_time":0.3142509989},
{"learn":[184.4333631],"iteration":712,"passed_time":0.7779710945,"remaining_time":0.3131524602},
{"learn":[183.4820113],"iteration":713,"passed_time":0.7791003369,"remaining_time":0.3120766055},
{"learn":[182.5454706],"iteration":714,"passed_time":0.7801767542,"remaining_time":0.3109795454},
{"learn":[182.3516562],"iteration":715,"passed_time":0.7812122179,"remaining_time":0.3098662987},
{"learn":[181.4172914],"iteration":716,"passed_time":0.7822634599,"remaining_time":0.3087594967},
{"learn":[180.6139505],"iteration":717,"passed_time":0.783331933,"remaining_time":0.3076596171},
{"learn":[179.940612],"iteration":718,"passed_time":0.7843938543,"remaining_time":0.3065572643},
{"learn":[179.7857625],"iteration":719,"passed_time":0.7854169957,"remaining_time":0.3054399428},
{"learn":[179.2563754],"iteration":720,"passed_time":0.7864854688,"remaining_time":0.3043404241},
{"learn":[178.6361158],"iteration":721,"passed_time":0.7876231226,"remaining_time":0.3032676289},
{"learn":[177.2579418],"iteration":722,"passed_time":0.7888110206,"remaining_time":0.3022139042},
{"learn":[176.801962],"iteration":723,"passed_time":0.7899582254,"remaining_time":0.3011442959},
{"learn":[176.3346798],"iteration":724,"passed_time":0.7911404031,"remaining_time":0.3000877391},
{"learn":[175.926189],"iteration":725,"passed_time":0.792373443,"remaining_time":0.2990500322},
{"learn":[174.8651043],"iteration":726,"passed_time":0.793476338,"remaining_time":0.2979629165},
{"learn":[174.5940831],"iteration":727,"passed_time":0.7945500205,"remaining_time":0.2968648428},
{"learn":[173.5506764],"iteration":728,"passed_time":0.7956319978,"remaining_time":0.2957699196},
{"learn":[173.1675809],"iteration":729,"passed_time":0.7967206171,"remaining_time":0.2946774885},
{"learn":[172.3175683],"iteration":730,"passed_time":0.7977492986,"remaining_time":0.2935630114},
{"learn":[171.4317927],"iteration":731,"passed_time":0.798828511,"remaining_time":0.292467269},
{"learn":[170.7085668],"iteration":732,"passed_time":0.7998913238,"remaining_time":0.2913655982},
{"learn":[170.5162332],"iteration":733,"passed_time":0.8009731409,"remaining_time":0.2902709203},
{"learn":[170.3416121],"iteration":734,"passed_time":0.8020257454,"remaining_time":0.2891657449},
{"learn":[169.8668019],"iteration":735,"passed_time":0.8030893397,"remaining_time":0.2880646545},
{"learn":[169.7447913],"iteration":736,"passed_time":0.8041411428,"remaining_time":0.286959458},
{"learn":[169.2479593],"iteration":737,"passed_time":0.8052201748,"remaining_time":0.2858640729},
{"learn":[169.1003628],"iteration":738,"passed_time":0.8063329089,"remaining_time":0.284780635},
{"learn":[168.8464689],"iteration":739,"passed_time":0.8074419049,"remaining_time":0.2836958044},
{"learn":[167.6896593],"iteration":740,"passed_time":0.8085192139,"remaining_time":0.2825998332},
{"learn":[167.5274339],"iteration":741,"passed_time":0.8095512113,"remaining_time":0.281488157},
{"learn":[167.0190539],"iteration":742,"passed_time":0.8106130825,"remaining_time":0.2803870285},
{"learn":[166.8615588],"iteration":743,"passed_time":0.811671788,"remaining_time":0.2792849163},
{"learn":[165.9322918],"iteration":744,"passed_time":0.8127276684,"remaining_time":0.2781819536},
{"learn":[165.6137201],"iteration":745,"passed_time":0.8137815552,"remaining_time":0.2770784384},
{"learn":[164.5173692],"iteration":746,"passed_time":0.8148409619,"remaining_time":0.2759769255},
{"learn":[163.7404206],"iteration":747,"passed_time":0.81589554,"remaining_time":0.2748738985},
{"learn":[163.5503491],"iteration":748,"passed_time":0.8169655959,"remaining_time":0.2737761877},
{"learn":[162.7472574],"iteration":749,"passed_time":0.8180434258,"remaining_time":0.2726811419},
{"learn":[161.9068014],"iteration":750,"passed_time":0.8191055073,"remaining_time":0.2715809205},
{"learn":[161.1558386],"iteration":751,"passed_time":0.8201694422,"remaining_time":0.2704814118},
{"learn":[160.1773449],"iteration":752,"passed_time":0.8213305879,"remaining_time":0.2694138848},
{"learn":[159.7733233],"iteration":753,"passed_time":0.8224678583,"remaining_time":0.2683383198},
{"learn":[159.6430846],"iteration":754,"passed_time":0.8235510178,"remaining_time":0.2672450323},
{"learn":[158.8544162],"iteration":755,"passed_time":0.8246389158,"remaining_time":0.2661533009},
{"learn":[158.645528],"iteration":756,"passed_time":0.8257112758,"remaining_time":0.2650565918},
{"learn":[158.0205793],"iteration":757,"passed_time":0.8267883343,"remaining_time":0.2639614471},
{"learn":[157.2802081],"iteration":758,"passed_time":0.827836581,"remaining_time":0.2628572016},
{"learn":[156.7235046],"iteration":759,"passed_time":0.8289052945,"remaining_time":0.2617595667},
{"learn":[156.3636839],"iteration":760,"passed_time":0.8299536013,"remaining_time":0.2606555988},
{"learn":[155.705678],"iteration":761,"passed_time":0.8310115454,"remaining_time":0.2595547871},
{"learn":[155.0883327],"iteration":762,"passed_time":0.8320628175,"remaining_time":0.2584520154},
{"learn":[154.7174788],"iteration":763,"passed_time":0.8331258708,"remaining_time":0.2573530177},
{"learn":[154.3915117],"iteration":764,"passed_time":0.8341824224,"remaining_time":0.2562521167},
{"learn":[153.6643839],"iteration":765,"passed_time":0.8354791521,"remaining_time":0.2552247018},
{"learn":[153.476611],"iteration":766,"passed_time":0.8367573164,"remaining_time":0.2541909449},
{"learn":[153.1059838],"iteration":767,"passed_time":0.8378471679,"remaining_time":0.2530996653},
{"learn":[152.6324196],"iteration":768,"passed_time":0.8389331124,"remaining_time":0.2520072158},
{"learn":[152.0791856],"iteration":769,"passed_time":0.8400069351,"remaining_time":0.2509111624},
{"learn":[151.269699],"iteration":770,"passed_time":0.8410916274,"remaining_time":0.2498183952},
{"learn":[150.9291924],"iteration":771,"passed_time":0.8421466863,"remaining_time":0.248716897},
{"learn":[150.6061132],"iteration":772,"passed_time":0.8432012042,"remaining_time":0.2476153601},
{"learn":[149.6892411],"iteration":773,"passed_time":0.8442693367,"remaining_time":0.24651792},
{"learn":[149.2710786],"iteration":774,"passed_time":0.8453511938,"remaining_time":0.2454245401},
{"learn":[148.7648808],"iteration":775,"passed_time":0.8464160303,"remaining_time":0.2443262768},
{"learn":[147.8210788],"iteration":776,"passed_time":0.8476214858,"remaining_time":0.2432684573},
{"learn":[147.5380266],"iteration":777,"passed_time":0.8486855409,"remaining_time":0.2421699101},
{"learn":[147.247962],"iteration":778,"passed_time":0.8498855462,"remaining_time":0.2411100202},
{"learn":[146.7207035],"iteration":779,"passed_time":0.8510087678,"remaining_time":0.240028114},
{"learn":[146.2741184],"iteration":780,"passed_time":0.8520686454,"remaining_time":0.2389283398},
{"learn":[145.4485154],"iteration":781,"passed_time":0.8532021507,"remaining_time":0.2378491929},
{"learn":[144.6240468],"iteration":782,"passed_time":0.8544290638,"remaining_time":0.2367957942},
{"learn":[144.377446],"iteration":783,"passed_time":0.8554828103,"remaining_time":0.2356942437},
{"learn":[143.3842546],"iteration":784,"passed_time":0.8565397626,"remaining_time":0.234593693},
{"learn":[142.8561384],"iteration":785,"passed_time":0.8575941704,"remaining_time":0.2334925604},
{"learn":[142.6659294],"iteration":786,"passed_time":0.8586491091,"remaining_time":0.2323916903},
{"learn":[142.3086821],"iteration":787,"passed_time":0.8597864312,"remaining_time":0.2313131008},
{"learn":[142.0651409],"iteration":788,"passed_time":0.8608760924,"remaining_time":0.2302216166},
{"learn":[141.4724459],"iteration":789,"passed_time":0.8619464589,"remaining_time":0.2291250081},
{"learn":[141.0000389],"iteration":790,"passed_time":0.8630068574,"remaining_time":0.2280258321},
{"learn":[140.3880737],"iteration":791,"passed_time":0.8640632988,"remaining_time":0.2269257148},
{"learn":[140.2068209],"iteration":792,"passed_time":0.8651732794,"remaining_time":0.2258396833},
{"learn":[139.7415789],"iteration":793,"passed_time":0.86631265,"remaining_time":0.2247612165},
{"learn":[139.2656591],"iteration":794,"passed_time":0.8673823052,"remaining_time":0.2236646196},
{"learn":[139.141812],"iteration":795,"passed_time":0.868437835,"remaining_time":0.2225644703},
{"learn":[138.2248718],"iteration":796,"passed_time":0.8694993054,"remaining_time":0.2214659461},
{"learn":[137.275063],"iteration":797,"passed_time":0.8705669843,"remaining_time":0.2203690863},
{"learn":[136.7446261],"iteration":798,"passed_time":0.8716356377,"remaining_time":0.2192725446},
{"learn":[136.6209018],"iteration":799,"passed_time":0.8726527383,"remaining_time":0.2181631846},
{"learn":[136.5166432],"iteration":800,"passed_time":0.8736608026,"remaining_time":0.2170518099},
{"learn":[135.9452138],"iteration":801,"passed_time":0.8747264506,"remaining_time":0.2159549092},
{"learn":[135.4715739],"iteration":802,"passed_time":0.8757677047,"remaining_time":0.2148521019},
{"learn":[135.3661509],"iteration":803,"passed_time":0.8767962559,"remaining_time":0.2137463509},
{"learn":[134.8412632],"iteration":804,"passed_time":0.8778528576,"remaining_time":0.2126475866},
{"learn":[134.0277662],"iteration":805,"passed_time":0.8789658356,"remaining_time":0.2115624964},
{"learn":[133.3571352],"iteration":806,"passed_time":0.8800520005,"remaining_time":0.2104709245},
{"learn":[132.7408678],"iteration":807,"passed_time":0.8811026214,"remaining_time":0.2093709199},
{"learn":[132.0165631],"iteration":808,"passed_time":0.882166406,"remaining_time":0.2082741453},
{"learn":[131.4949344],"iteration":809,"passed_time":0.8833621975,"remaining_time":0.2072084167},
{"learn":[131.2913452],"iteration":810,"passed_time":0.8844263228,"remaining_time":0.2061116831},
{"learn":[130.8438553],"iteration":811,"passed_time":0.8855101134,"remaining_time":0.2050195829},
{"learn":[130.6866031],"iteration":812,"passed_time":0.8865821529,"remaining_time":0.2039248002},
{"learn":[130.472247],"iteration":813,"passed_time":0.8876414294,"remaining_time":0.2028271571},
{"learn":[130.0276352],"iteration":814,"passed_time":0.8887203291,"remaining_time":0.2017340624},
{"learn":[129.758498],"iteration":815,"passed_time":0.8897509641,"remaining_time":0.2006301194},
{"learn":[129.336268],"iteration":816,"passed_time":0.8908108417,"remaining_time":0.1995329058},
{"learn":[128.7017428],"iteration":817,"passed_time":0.8918924484,"remaining_time":0.1984406181},
{"learn":[128.5037732],"iteration":818,"passed_time":0.8929585973,"remaining_time":0.1973449403},
{"learn":[127.8252256],"iteration":819,"passed_time":0.8941531673,"remaining_time":0.1962775245},
{"learn":[127.4851497],"iteration":820,"passed_time":0.8952148481,"remaining_time":0.1951808256},
{"learn":[127.3846938],"iteration":821,"passed_time":0.8962518445,"remaining_time":0.1940788666},
{"learn":[126.8443591],"iteration":822,"passed_time":0.8972944911,"remaining_time":0.1929782806},
{"learn":[126.7000357],"iteration":823,"passed_time":0.8983542685,"remaining_time":0.1918814942},
{"learn":[126.612527],"iteration":824,"passed_time":0.8994076544,"remaining_time":0.1907834418},
{"learn":[126.3874246],"iteration":825,"passed_time":0.9004949514,"remaining_time":0.1896926411},
{"learn":[125.6828167],"iteration":826,"passed_time":0.9015603088,"remaining_time":0.1885972593},
{"learn":[125.5837278],"iteration":827,"passed_time":0.9026150772,"remaining_time":0.1874997503},
{"learn":[125.1287592],"iteration":828,"passed_time":0.9036671608,"remaining_time":0.1864017907},
{"learn":[124.6974653],"iteration":829,"passed_time":0.904735704,"remaining_time":0.1853073129},
{"learn":[124.3792802],"iteration":830,"passed_time":0.9057931071,"remaining_time":0.1842106319},
{"learn":[124.2465267],"iteration":831,"passed_time":0.9068414038,"remaining_time":0.1831122065},
{"learn":[124.103718],"iteration":832,"passed_time":0.9079055692,"remaining_time":0.1820170829},
{"learn":[123.6560073],"iteration":833,"passed_time":0.9090909357,"remaining_time":0.1809461575},
{"learn":[123.1587374],"iteration":834,"passed_time":0.9101246362,"remaining_time":0.179844988},
{"learn":[123.0438248],"iteration":835,"passed_time":0.9111485591,"remaining_time":0.1787420618},
{"learn":[122.7375515],"iteration":836,"passed_time":0.9121994004,"remaining_time":0.1776445666},
{"learn":[122.0656111],"iteration":837,"passed_time":0.9133010932,"remaining_time":0.1765570133},
{"learn":[121.5244404],"iteration":838,"passed_time":0.9143607604,"remaining_time":0.1754613617},
{"learn":[121.3478834],"iteration":839,"passed_time":0.9154205579,"remaining_time":0.1743658206},
{"learn":[120.9685948],"iteration":840,"passed_time":0.9164808061,"remaining_time":0.1732704497},
{"learn":[120.1441514],"iteration":841,"passed_time":0.9175486581,"remaining_time":0.172176589},
{"learn":[119.6044135],"iteration":842,"passed_time":0.918609828,"remaining_time":0.1710815457},
{"learn":[119.2531804],"iteration":843,"passed_time":0.919698277,"remaining_time":0.1699916247},
{"learn":[118.7678081],"iteration":844,"passed_time":0.9208195351,"remaining_time":0.1689077254},
{"learn":[118.2880349],"iteration":845,"passed_time":0.9218955016,"remaining_time":0.1678154932},
{"learn":[117.59702],"iteration":846,"passed_time":0.9229888495,"remaining_time":0.1667264392},
{"learn":[117.0449742],"iteration":847,"passed_time":0.9240284305,"remaining_time":0.1656277375},
{"learn":[116.9458211],"iteration":848,"passed_time":0.9250779094,"remaining_time":0.1645309356},
{"learn":[116.4332322],"iteration":849,"passed_time":0.9261569715,"remaining_time":0.1634394656},
{"learn":[116.0005374],"iteration":850,"passed_time":0.9272032947,"remaining_time":0.1623422925},
{"learn":[115.5373797],"iteration":851,"passed_time":0.9282815854,"remaining_time":0.1612507918},
{"learn":[115.0863353],"iteration":852,"passed_time":0.9293471132,"remaining_time":0.1601571227},
{"learn":[114.4723933],"iteration":853,"passed_time":0.9304179405,"remaining_time":0.1590644254},
{"learn":[114.1256973],"iteration":854,"passed_time":0.9314698337,"remaining_time":0.1579685683},
{"learn":[113.7131109],"iteration":855,"passed_time":0.9325314344,"remaining_time":0.1568744469},
{"learn":[113.2698902],"iteration":856,"passed_time":0.9336098954,"remaining_time":0.1557832148},
{"learn":[112.8853423],"iteration":857,"passed_time":0.9346772265,"remaining_time":0.1546901703},
{"learn":[112.4571833],"iteration":858,"passed_time":0.9357280878,"remaining_time":0.1535944824},
{"learn":[111.8246711],"iteration":859,"passed_time":0.9367735795,"remaining_time":0.1524980246},
{"learn":[111.5102998],"iteration":860,"passed_time":0.9378314936,"remaining_time":0.1514036906},
{"learn":[111.1477208],"iteration":861,"passed_time":0.938915715,"remaining_time":0.1503136527},
{"learn":[110.6656655],"iteration":862,"passed_time":0.9399740899,"remaining_time":0.1492195253},
{"learn":[110.1457008],"iteration":863,"passed_time":0.9410790786,"remaining_time":0.1481328179},
{"learn":[109.8614464],"iteration":864,"passed_time":0.9421370328,"remaining_time":0.1470387277},
{"learn":[109.7148338],"iteration":865,"passed_time":0.9432155339,"remaining_time":0.1459479002},
{"learn":[109.4931927],"iteration":866,"passed_time":0.9442726765,"remaining_time":0.1448538247},
{"learn":[109.1252591],"iteration":867,"passed_time":0.9453333055,"remaining_time":0.1437603644},
{"learn":[108.5388659],"iteration":868,"passed_time":0.946384828,"remaining_time":0.142665607},
{"learn":[108.044599],"iteration":869,"passed_time":0.9474435636,"remaining_time":0.1415720267},
{"learn":[107.8271394],"iteration":870,"passed_time":0.9485060659,"remaining_time":0.1404790844},
{"learn":[107.5569479],"iteration":871,"passed_time":0.9495179371,"remaining_time":0.1393787798},
{"learn":[107.1898866],"iteration":872,"passed_time":0.9506226954,"remaining_time":0.1382921905},
{"learn":[106.9327676],"iteration":873,"passed_time":0.9517300892,"remaining_time":0.1372059396},
{"learn":[106.4718169],"iteration":874,"passed_time":0.9528064064,"remaining_time":0.1361152009},
{"learn":[106.1957365],"iteration":875,"passed_time":0.9538571876,"remaining_time":0.1350208804},
{"learn":[106.0869032],"iteration":876,"passed_time":0.9549197801,"remaining_time":0.1339283158},
{"learn":[105.726112],"iteration":877,"passed_time":0.9559666443,"remaining_time":0.1328336339},
{"learn":[105.1987868],"iteration":878,"passed_time":0.9570187379,"remaining_time":0.1317397808},
{"learn":[104.7480571],"iteration":879,"passed_time":0.9580770426,"remaining_time":0.1306468694},
{"learn":[104.3839461],"iteration":880,"passed_time":0.9591578679,"remaining_time":0.1295570786},
{"learn":[104.2070463],"iteration":881,"passed_time":0.960217485,"remaining_time":0.1284644708},
{"learn":[103.4844776],"iteration":882,"passed_time":0.9613000034,"remaining_time":0.1273749721},
{"learn":[103.0204133],"iteration":883,"passed_time":0.9623830226,"remaining_time":0.126285555},
{"learn":[102.4325532],"iteration":884,"passed_time":0.9634523472,"remaining_time":0.1251943728},
{"learn":[102.2126336],"iteration":885,"passed_time":0.9645205798,"remaining_time":0.1241030994},
{"learn":[101.8945749],"iteration":886,"passed_time":0.9655705496,"remaining_time":0.1230095514},
{"learn":[101.5612713],"iteration":887,"passed_time":0.9667800866,"remaining_time":0.1219362271},
{"learn":[100.977361],"iteration":888,"passed_time":0.9678396636,"remaining_time":0.1208438725},
{"learn":[100.6992661],"iteration":889,"passed_time":0.9689098197,"remaining_time":0.1197528991},
{"learn":[100.5354913],"iteration":890,"passed_time":0.9699413062,"remaining_time":0.1186572417},
{"learn":[100.1497609],"iteration":891,"passed_time":0.9709963751,"remaining_time":0.1175645835},
{"learn":[99.56437269],"iteration":892,"passed_time":0.9720587873,"remaining_time":0.1164728894},
{"learn":[99.38928004],"iteration":893,"passed_time":0.9731273505,"remaining_time":0.1153819901},
{"learn":[99.00570592],"iteration":894,"passed_time":0.9742057214,"remaining_time":0.1142922913},
{"learn":[98.67178276],"iteration":895,"passed_time":0.9752644068,"remaining_time":0.1132003329},
{"learn":[98.32908952],"iteration":896,"passed_time":0.9763176024,"remaining_time":0.1121078183},
{"learn":[98.25231459],"iteration":897,"passed_time":0.9773420963,"remaining_time":0.1110121312},
{"learn":[97.74654753],"iteration":898,"passed_time":0.9784251356,"remaining_time":0.1099231799},
{"learn":[97.42891746],"iteration":899,"passed_time":0.9794836206,"remaining_time":0.1088315134},
{"learn":[97.25110634],"iteration":900,"passed_time":0.9808163168,"remaining_time":0.1077700504},
{"learn":[97.0588188],"iteration":901,"passed_time":0.9820241708,"remaining_time":0.1066944221},
{"learn":[96.61297273],"iteration":902,"passed_time":0.9831256633,"remaining_time":0.1056070757},
{"learn":[96.49320757],"iteration":903,"passed_time":0.9842025314,"remaining_time":0.104517083},
{"learn":[96.30329171],"iteration":904,"passed_time":0.985275202,"remaining_time":0.1034266787},
{"learn":[95.80959363],"iteration":905,"passed_time":0.9863448572,"remaining_time":0.1023360006},
{"learn":[95.49133838],"iteration":906,"passed_time":0.9874132602,"remaining_time":0.1012452406},
{"learn":[95.11313159],"iteration":907,"passed_time":0.988501124,"remaining_time":0.1001565015},
{"learn":[94.78968172],"iteration":908,"passed_time":0.9895529571,"remaining_time":0.09906415742},
{"learn":[94.64556407],"iteration":909,"passed_time":0.990625227,"remaining_time":0.09797392355},
{"learn":[94.17554933],"iteration":910,"passed_time":0.9916997009,"remaining_time":0.09688394443},
{"learn":[93.77255123],"iteration":911,"passed_time":0.992774335,"remaining_time":0.09579401478},
{"learn":[93.49227688],"iteration":912,"passed_time":0.993842758,"remaining_time":0.09470352677},
{"learn":[93.14989281],"iteration":913,"passed_time":0.9950546233,"remaining_time":0.09362658381},
{"learn":[92.97335097],"iteration":914,"passed_time":0.9961374922,"remaining_time":0.09253736267},
{"learn":[92.59651375],"iteration":915,"passed_time":0.9972179468,"remaining_time":0.09144793399},
{"learn":[92.52881049],"iteration":916,"passed_time":0.998237031,"remaining_time":0.09035297009},
{"learn":[92.19508269],"iteration":917,"passed_time":0.9992983612,"remaining_time":0.08926194512},
{"learn":[91.80840975],"iteration":918,"passed_time":1.000408549,"remaining_time":0.08817529108},
{"learn":[91.25939266],"iteration":919,"passed_time":1.001513739,"remaining_time":0.08708815117},
{"learn":[90.99048522],"iteration":920,"passed_time":1.002566423,"remaining_time":0.08599646844},
{"learn":[90.52986361],"iteration":921,"passed_time":1.003615912,"remaining_time":0.08490459993},
{"learn":[90.12435701],"iteration":922,"passed_time":1.004685868,"remaining_time":0.08381453068},
{"learn":[89.72718666],"iteration":923,"passed_time":1.005782481,"remaining_time":0.08272669761},
{"learn":[89.33837827],"iteration":924,"passed_time":1.006850634,"remaining_time":0.08163653789},
{"learn":[88.81931862],"iteration":925,"passed_time":1.007918496,"remaining_time":0.08054640248},
{"learn":[88.55148247],"iteration":926,"passed_time":1.008985466,"remaining_time":0.07945624492},
{"learn":[88.40749613],"iteration":927,"passed_time":1.010147534,"remaining_time":0.07837351554},
{"learn":[87.82915038],"iteration":928,"passed_time":1.01121774,"remaining_time":0.07728359476},
{"learn":[87.4807444],"iteration":929,"passed_time":1.012281915,"remaining_time":0.07619326243},
{"learn":[87.00954836],"iteration":930,"passed_time":1.013325423,"remaining_time":0.07510145457},
{"learn":[86.61903883],"iteration":931,"passed_time":1.014397383,"remaining_time":0.0740118262},
{"learn":[86.42606692],"iteration":932,"passed_time":1.015438537,"remaining_time":0.07292002352},
{"learn":[86.35183876],"iteration":933,"passed_time":1.016461087,"remaining_time":0.07182701471},
{"learn":[86.10304465],"iteration":934,"passed_time":1.017530812,"remaining_time":0.07073743614},
{"learn":[85.7272468],"iteration":935,"passed_time":1.018583357,"remaining_time":0.06964672524},
{"learn":[85.651157],"iteration":936,"passed_time":1.019645869,"remaining_time":0.068556766},
{"learn":[85.2465328],"iteration":937,"passed_time":1.020717898,"remaining_time":0.06746749435},
{"learn":[84.90308621],"iteration":938,"passed_time":1.021781863,"remaining_time":0.06637773553},
{"learn":[84.43813826],"iteration":939,"passed_time":1.022800206,"remaining_time":0.06528511955},
{"learn":[83.98374815],"iteration":940,"passed_time":1.024628783,"remaining_time":0.06424346247},
{"learn":[83.78898891],"iteration":941,"passed_time":1.026085955,"remaining_time":0.06317726686},
{"learn":[83.42770613],"iteration":942,"passed_time":1.027437205,"remaining_time":0.06210383956},
{"learn":[82.97769748],"iteration":943,"passed_time":1.02882259,"remaining_time":0.06103184857},
{"learn":[82.5236236],"iteration":944,"passed_time":1.030067397,"remaining_time":0.0599510125},
{"learn":[82.27728876],"iteration":945,"passed_time":1.031336745,"remaining_time":0.0588712307},
{"learn":[82.08540175],"iteration":946,"passed_time":1.032651271,"remaining_time":0.05779357695},
{"learn":[81.81499982],"iteration":947,"passed_time":1.03393095,"remaining_time":0.05671351204},
{"learn":[81.56968775],"iteration":948,"passed_time":1.035247963,"remaining_time":0.05563503281},
{"learn":[81.27998918],"iteration":949,"passed_time":1.036401219,"remaining_time":0.05454743258},
{"learn":[81.07086801],"iteration":950,"passed_time":1.037552451,"remaining_time":0.05345959001},
{"learn":[80.61150542],"iteration":951,"passed_time":1.038639878,"remaining_time":0.05236839722},
{"learn":[80.21798278],"iteration":952,"passed_time":1.039717379,"remaining_time":0.05127672278},
{"learn":[79.72532454],"iteration":953,"passed_time":1.040865131,"remaining_time":0.05018846541},
{"learn":[79.36476527],"iteration":954,"passed_time":1.042084675,"remaining_time":0.04910346638},
{"learn":[79.02437077],"iteration":955,"passed_time":1.043169248,"remaining_time":0.04801197374},
{"learn":[78.64179191],"iteration":956,"passed_time":1.044260582,"remaining_time":0.04692079939},
{"learn":[78.19651868],"iteration":957,"passed_time":1.045333463,"remaining_time":0.04582881569},
{"learn":[77.82708764],"iteration":958,"passed_time":1.046400273,"remaining_time":0.04473661229},
{"learn":[77.47152488],"iteration":959,"passed_time":1.047618458,"remaining_time":0.04365076909},
{"learn":[77.40115767],"iteration":960,"passed_time":1.048710984,"remaining_time":0.04255955088},
{"learn":[77.19469985],"iteration":961,"passed_time":1.049777314,"remaining_time":0.04146729513},
{"learn":[77.12776002],"iteration":962,"passed_time":1.050821693,"remaining_time":0.0403742499},
{"learn":[76.7986258],"iteration":963,"passed_time":1.051891108,"remaining_time":0.03928224055},
{"learn":[76.57241997],"iteration":964,"passed_time":1.053121765,"remaining_time":0.0381961262},
{"learn":[76.36739564],"iteration":965,"passed_time":1.054222466,"remaining_time":0.03710513856},
{"learn":[76.15833167],"iteration":966,"passed_time":1.055297401,"remaining_time":0.03601325153},
{"learn":[75.82084693],"iteration":967,"passed_time":1.056394546,"remaining_time":0.03492213374},
{"learn":[75.72061387],"iteration":968,"passed_time":1.057455064,"remaining_time":0.03382983178},
{"learn":[75.65453777],"iteration":969,"passed_time":1.058513469,"remaining_time":0.03273752998},
{"learn":[75.40360591],"iteration":970,"passed_time":1.059637993,"remaining_time":0.03164727271},
{"learn":[75.13791177],"iteration":971,"passed_time":1.060743714,"remaining_time":0.03055640327},
{"learn":[75.00795871],"iteration":972,"passed_time":1.06182535,"remaining_time":0.029464835},
{"learn":[74.59761716],"iteration":973,"passed_time":1.062899524,"remaining_time":0.0283730879},
{"learn":[74.42442763],"iteration":974,"passed_time":1.063956055,"remaining_time":0.02728092449},
{"learn":[74.23735367],"iteration":975,"passed_time":1.064979317,"remaining_time":0.02618801599},
{"learn":[74.04090566],"iteration":976,"passed_time":1.066062506,"remaining_time":0.02509666085},
{"learn":[73.67679905],"iteration":977,"passed_time":1.067104422,"remaining_time":0.02400439395},
{"learn":[73.41487506],"iteration":978,"passed_time":1.068257938,"remaining_time":0.02291462379},
{"learn":[73.3257422],"iteration":979,"passed_time":1.069334806,"remaining_time":0.02182315931},
{"learn":[73.09782574],"iteration":980,"passed_time":1.070399703,"remaining_time":0.02073149271},
{"learn":[72.90946936],"iteration":981,"passed_time":1.071460943,"remaining_time":0.01963981361},
{"learn":[72.63528887],"iteration":982,"passed_time":1.072535657,"remaining_time":0.01854842947},
{"learn":[72.18258749],"iteration":983,"passed_time":1.073611724,"remaining_time":0.0174571012},
{"learn":[71.79183567],"iteration":984,"passed_time":1.074671641,"remaining_time":0.01636555799},
{"learn":[71.6009998],"iteration":985,"passed_time":1.075745925,"remaining_time":0.01527428291},
{"learn":[71.42764296],"iteration":986,"passed_time":1.076785025,"remaining_time":0.01418257885},
{"learn":[71.25821243],"iteration":987,"passed_time":1.077862835,"remaining_time":0.01309145144},
{"learn":[70.9765156],"iteration":988,"passed_time":1.078918936,"remaining_time":0.0120001095},
{"learn":[70.64382628],"iteration":989,"passed_time":1.079972913,"remaining_time":0.0109088173},
{"learn":[70.32700451],"iteration":990,"passed_time":1.081023984,"remaining_time":0.009817574026},
{"learn":[70.08201276],"iteration":991,"passed_time":1.08213259,"remaining_time":0.008726875724},
{"learn":[69.94696336],"iteration":992,"passed_time":1.083207905,"remaining_time":0.007635906683},
{"learn":[69.66814946],"iteration":993,"passed_time":1.084261501,"remaining_time":0.006544838037},
{"learn":[69.47314904],"iteration":994,"passed_time":1.085322982,"remaining_time":0.005453884331},
{"learn":[69.16965844],"iteration":995,"passed_time":1.086374785,"remaining_time":0.004362950944},
{"learn":[69.09089917],"iteration":996,"passed_time":1.087423442,"remaining_time":0.003272086587},
{"learn":[69.03063738],"iteration":997,"passed_time":1.088461891,"remaining_time":0.002181286355},
{"learn":[68.74925968],"iteration":998,"passed_time":1.08954482,"remaining_time":0.001090635456},
{"learn":[68.34172948],"iteration":999,"passed_time":1.090646203,"remaining_time":0}
]}